{
  "_comment" : "Created with OWL2VOWL (version 0.3.5), http://vowl.visualdataweb.org",
  "header" : {
    "languages" : [ "en", "undefined" ],
    "baseIris" : [ "https://codemeta.github.io/terms", "http://www.w3.org/1999/02/22-rdf-syntax-ns", "http://www.geoscienceontology.org/geo-upper", "http://qudt.org/schema/qudt", "http://schema.org", "http://www.w3.org/2002/07/owl", "http://www.w3.org/2000/01/rdf-schema", "http://www.w3.org/ns/prov", "https://w3id.org/okn/o/sd", "http://www.w3.org/2001/XMLSchema", "http://purl.org/linked-data/cube" ],
    "title" : {
      "en" : "The Software Description Ontology"
    },
    "iri" : "https://w3id.org/okn/o/sd",
    "version" : "1.6.0",
    "author" : [ "Yolanda Gil", "Deborah Khider", "Varun Ratnakar", "Daniel Garijo" ],
    "comments" : {
      "en" : "An ontology for describing software and their links to inputs, outputs and variables"
    },
    "other" : {
      "license" : [ {
        "identifier" : "license",
        "language" : "undefined",
        "value" : "http://creativecommons.org/licenses/by/2.0/",
        "type" : "iri"
      } ],
      "priorVersion" : [ {
        "identifier" : "priorVersion",
        "language" : "undefined",
        "value" : "https://w3id.org/okn/o/sd/1.5.0",
        "type" : "iri"
      } ],
      "creator" : [ {
        "identifier" : "creator",
        "language" : "en",
        "value" : "Yolanda Gil",
        "type" : "label"
      }, {
        "identifier" : "creator",
        "language" : "en",
        "value" : "Varun Ratnakar",
        "type" : "label"
      }, {
        "identifier" : "creator",
        "language" : "en",
        "value" : "Daniel Garijo",
        "type" : "label"
      }, {
        "identifier" : "creator",
        "language" : "undefined",
        "value" : "Deborah Khider",
        "type" : "label"
      } ],
      "contributor" : [ {
        "identifier" : "contributor",
        "language" : "undefined",
        "value" : "Hernan Vargas",
        "type" : "label"
      }, {
        "identifier" : "contributor",
        "language" : "undefined",
        "value" : "Maximiliano Osorio",
        "type" : "label"
      } ],
      "created" : [ {
        "identifier" : "created",
        "language" : "undefined",
        "value" : "May 28th, 2020",
        "type" : "label"
      } ],
      "preferredNamespacePrefix" : [ {
        "identifier" : "preferredNamespacePrefix",
        "language" : "en",
        "value" : "sd",
        "type" : "label"
      } ],
      "preferredNamespaceUri" : [ {
        "identifier" : "preferredNamespaceUri",
        "language" : "undefined",
        "value" : "https://w3id.org/okn/o/sd",
        "type" : "iri"
      } ],
      "versionInfo" : [ {
        "identifier" : "versionInfo",
        "language" : "undefined",
        "value" : "1.6.0",
        "type" : "label"
      } ],
      "abstract" : [ {
        "identifier" : "abstract",
        "language" : "en",
        "value" : "An ontology for describing software and their links to inputs, outputs and variables",
        "type" : "label"
      } ],
      "title" : [ {
        "identifier" : "title",
        "language" : "en",
        "value" : "The Software Description Ontology",
        "type" : "label"
      } ]
    }
  },
  "namespace" : [ ],
  "class" : [ {
    "id" : "19",
    "type" : "owl:Class"
  }, {
    "id" : "8",
    "type" : "owl:Class"
  }, {
    "id" : "29",
    "type" : "owl:Class"
  }, {
    "id" : "37",
    "type" : "owl:Class"
  }, {
    "id" : "39",
    "type" : "owl:Class"
  }, {
    "id" : "81",
    "type" : "owl:Class"
  }, {
    "id" : "20",
    "type" : "owl:Class"
  }, {
    "id" : "72",
    "type" : "owl:Class"
  }, {
    "id" : "79",
    "type" : "owl:Class"
  }, {
    "id" : "120",
    "type" : "owl:Class"
  }, {
    "id" : "12",
    "type" : "owl:Class"
  }, {
    "id" : "134",
    "type" : "owl:Class"
  }, {
    "id" : "38",
    "type" : "owl:Class"
  }, {
    "id" : "74",
    "type" : "rdfs:Datatype"
  }, {
    "id" : "45",
    "type" : "owl:Class"
  }, {
    "id" : "41",
    "type" : "owl:Class"
  }, {
    "id" : "25",
    "type" : "owl:Class"
  }, {
    "id" : "164",
    "type" : "rdfs:Datatype"
  }, {
    "id" : "165",
    "type" : "owl:unionOf"
  }, {
    "id" : "167",
    "type" : "rdfs:Datatype"
  }, {
    "id" : "51",
    "type" : "owl:Class"
  }, {
    "id" : "2",
    "type" : "rdfs:Datatype"
  }, {
    "id" : "28",
    "type" : "rdfs:Datatype"
  }, {
    "id" : "62",
    "type" : "rdfs:Datatype"
  }, {
    "id" : "170",
    "type" : "rdfs:Datatype"
  }, {
    "id" : "171",
    "type" : "owl:unionOf"
  }, {
    "id" : "172",
    "type" : "owl:unionOf"
  }, {
    "id" : "92",
    "type" : "rdfs:Datatype"
  }, {
    "id" : "15",
    "type" : "rdfs:Datatype"
  }, {
    "id" : "101",
    "type" : "rdfs:Datatype"
  }, {
    "id" : "151",
    "type" : "rdfs:Datatype"
  }, {
    "id" : "176",
    "type" : "rdfs:Datatype"
  }, {
    "id" : "177",
    "type" : "owl:unionOf"
  }, {
    "id" : "178",
    "type" : "rdfs:Datatype"
  }, {
    "id" : "179",
    "type" : "rdfs:Datatype"
  }, {
    "id" : "113",
    "type" : "rdfs:Datatype"
  }, {
    "id" : "163",
    "type" : "rdfs:Datatype"
  }, {
    "id" : "103",
    "type" : "rdfs:Datatype"
  }, {
    "id" : "141",
    "type" : "rdfs:Datatype"
  }, {
    "id" : "44",
    "type" : "owl:Class"
  }, {
    "id" : "185",
    "type" : "rdfs:Datatype"
  }, {
    "id" : "186",
    "type" : "rdfs:Datatype"
  }, {
    "id" : "1",
    "type" : "owl:Class"
  }, {
    "id" : "32",
    "type" : "owl:Class"
  }, {
    "id" : "194",
    "type" : "rdfs:Datatype"
  }, {
    "id" : "5",
    "type" : "rdfs:Datatype"
  }, {
    "id" : "147",
    "type" : "rdfs:Datatype"
  }, {
    "id" : "146",
    "type" : "owl:unionOf"
  }, {
    "id" : "195",
    "type" : "rdfs:Datatype"
  }, {
    "id" : "196",
    "type" : "rdfs:Datatype"
  }, {
    "id" : "4",
    "type" : "owl:unionOf"
  }, {
    "id" : "33",
    "type" : "rdfs:Datatype"
  }, {
    "id" : "132",
    "type" : "rdfs:Datatype"
  }, {
    "id" : "70",
    "type" : "rdfs:Datatype"
  }, {
    "id" : "67",
    "type" : "rdfs:Datatype"
  }, {
    "id" : "47",
    "type" : "owl:Class"
  }, {
    "id" : "159",
    "type" : "owl:unionOf"
  }, {
    "id" : "175",
    "type" : "rdfs:Datatype"
  }, {
    "id" : "13",
    "type" : "rdfs:Datatype"
  }, {
    "id" : "205",
    "type" : "owl:unionOf"
  }, {
    "id" : "144",
    "type" : "rdfs:Datatype"
  }, {
    "id" : "143",
    "type" : "owl:unionOf"
  }, {
    "id" : "153",
    "type" : "rdfs:Datatype"
  }, {
    "id" : "207",
    "type" : "rdfs:Datatype"
  }, {
    "id" : "57",
    "type" : "rdfs:Literal"
  }, {
    "id" : "55",
    "type" : "rdfs:Literal"
  }, {
    "id" : "181",
    "type" : "rdfs:Literal"
  }, {
    "id" : "65",
    "type" : "rdfs:Literal"
  }, {
    "id" : "22",
    "type" : "rdfs:Literal"
  }, {
    "id" : "30",
    "type" : "owl:Class"
  }, {
    "id" : "26",
    "type" : "owl:Class"
  }, {
    "id" : "117",
    "type" : "owl:Class"
  }, {
    "id" : "160",
    "type" : "rdfs:Literal"
  }, {
    "id" : "69",
    "type" : "owl:Class"
  }, {
    "id" : "157",
    "type" : "rdfs:Literal"
  }, {
    "id" : "210",
    "type" : "owl:unionOf"
  }, {
    "id" : "136",
    "type" : "owl:unionOf"
  }, {
    "id" : "17",
    "type" : "owl:Thing"
  }, {
    "id" : "211",
    "type" : "rdfs:Datatype"
  }, {
    "id" : "119",
    "type" : "rdfs:Datatype"
  }, {
    "id" : "124",
    "type" : "rdfs:Datatype"
  }, {
    "id" : "223",
    "type" : "rdfs:Datatype"
  }, {
    "id" : "224",
    "type" : "owl:unionOf"
  }, {
    "id" : "60",
    "type" : "owl:Class"
  }, {
    "id" : "122",
    "type" : "rdfs:Datatype"
  }, {
    "id" : "97",
    "type" : "rdfs:Datatype"
  }, {
    "id" : "111",
    "type" : "rdfs:Datatype"
  }, {
    "id" : "222",
    "type" : "rdfs:Datatype"
  }, {
    "id" : "221",
    "type" : "owl:unionOf"
  }, {
    "id" : "95",
    "type" : "rdfs:Datatype"
  }, {
    "id" : "155",
    "type" : "rdfs:Datatype"
  }, {
    "id" : "237",
    "type" : "rdfs:Literal"
  }, {
    "id" : "239",
    "type" : "rdfs:Literal"
  }, {
    "id" : "230",
    "type" : "owl:unionOf"
  }, {
    "id" : "240",
    "type" : "owl:unionOf"
  }, {
    "id" : "183",
    "type" : "owl:unionOf"
  }, {
    "id" : "115",
    "type" : "owl:unionOf"
  }, {
    "id" : "76",
    "type" : "owl:unionOf"
  }, {
    "id" : "188",
    "type" : "rdfs:Datatype"
  }, {
    "id" : "90",
    "type" : "rdfs:Datatype"
  }, {
    "id" : "243",
    "type" : "rdfs:Datatype"
  }, {
    "id" : "36",
    "type" : "owl:Class"
  }, {
    "id" : "10",
    "type" : "owl:Class"
  }, {
    "id" : "85",
    "type" : "owl:unionOf"
  }, {
    "id" : "7",
    "type" : "owl:Class"
  }, {
    "id" : "126",
    "type" : "owl:unionOf"
  }, {
    "id" : "249",
    "type" : "rdfs:Literal"
  }, {
    "id" : "247",
    "type" : "rdfs:Literal"
  }, {
    "id" : "251",
    "type" : "rdfs:Literal"
  }, {
    "id" : "149",
    "type" : "rdfs:Literal"
  }, {
    "id" : "127",
    "type" : "owl:Thing"
  }, {
    "id" : "219",
    "type" : "rdfs:Literal"
  }, {
    "id" : "137",
    "type" : "rdfs:Literal"
  }, {
    "id" : "130",
    "type" : "rdfs:Literal"
  }, {
    "id" : "53",
    "type" : "owl:Class"
  }, {
    "id" : "50",
    "type" : "owl:Class"
  }, {
    "id" : "217",
    "type" : "rdfs:Literal"
  }, {
    "id" : "78",
    "type" : "owl:Class"
  }, {
    "id" : "215",
    "type" : "rdfs:Literal"
  }, {
    "id" : "106",
    "type" : "owl:Thing"
  }, {
    "id" : "192",
    "type" : "rdfs:Literal"
  }, {
    "id" : "88",
    "type" : "rdfs:Literal"
  }, {
    "id" : "201",
    "type" : "rdfs:Literal"
  }, {
    "id" : "199",
    "type" : "rdfs:Literal"
  } ],
  "classAttribute" : [ {
    "iri" : "http://qudt.org/schema/qudt/Unit",
    "baseIri" : "http://qudt.org/schema/qudt",
    "instances" : 0,
    "annotations" : {
      "isDefinedBy" : [ {
        "identifier" : "isDefinedBy",
        "language" : "undefined",
        "value" : "http://qudt.org/schema/qudt/",
        "type" : "iri"
      } ]
    },
    "label" : {
      "IRI-based" : "Unit"
    },
    "subClasses" : [ "20" ],
    "attributes" : [ "external" ],
    "id" : "19"
  }, {
    "iri" : "https://w3id.org/okn/o/sd#SampleResource",
    "baseIri" : "https://w3id.org/okn/o/sd",
    "instances" : 0,
    "label" : {
      "IRI-based" : "SampleResource",
      "en" : "Sample Resource"
    },
    "subClasses" : [ "26" ],
    "comment" : {
      "en" : "A sample resource associated with a software"
    },
    "id" : "8",
    "superClasses" : [ "25" ]
  }, {
    "iri" : "https://w3id.org/okn/o/sd#Person",
    "baseIri" : "https://w3id.org/okn/o/sd",
    "instances" : 0,
    "label" : {
      "IRI-based" : "Person",
      "en" : "Person"
    },
    "id" : "29",
    "superClasses" : [ "30" ]
  }, {
    "iri" : "https://w3id.org/okn/o/sd#Variable",
    "baseIri" : "https://w3id.org/okn/o/sd",
    "instances" : 0,
    "label" : {
      "IRI-based" : "Variable",
      "en" : "Variable"
    },
    "subClasses" : [ "38", "39", "10" ],
    "comment" : {
      "en" : "A symbol that represents a quanity in a dataset or dataset specification"
    },
    "id" : "37"
  }, {
    "iri" : "https://w3id.org/okn/o/sd#NumericalIndex",
    "baseIri" : "https://w3id.org/okn/o/sd",
    "instances" : 0,
    "label" : {
      "IRI-based" : "NumericalIndex",
      "en" : "Numerical Index"
    },
    "comment" : {
      "en" : "A number (such as a ratio) derived from a series of observations and used as an indicator or measure (https://www.merriam-webster.com/dictionary/index)"
    },
    "id" : "39",
    "superClasses" : [ "37" ]
  }, {
    "iri" : "http://purl.org/linked-data/cube#DataStructureDefinition",
    "baseIri" : "http://purl.org/linked-data/cube",
    "instances" : 0,
    "annotations" : {
      "isDefinedBy" : [ {
        "identifier" : "isDefinedBy",
        "language" : "undefined",
        "value" : "http://purl.org/linked-data/cube#",
        "type" : "iri"
      } ]
    },
    "label" : {
      "IRI-based" : "DataStructureDefinition"
    },
    "subClasses" : [ "1" ],
    "attributes" : [ "external" ],
    "id" : "81"
  }, {
    "iri" : "https://w3id.org/okn/o/sd#Unit",
    "baseIri" : "https://w3id.org/okn/o/sd",
    "instances" : 0,
    "label" : {
      "IRI-based" : "Unit",
      "en" : "Unit"
    },
    "comment" : {
      "en" : "Class designed to distinguish the different types of units that are available in variables from datasets or parameters"
    },
    "id" : "20",
    "superClasses" : [ "19" ]
  }, {
    "iri" : "https://w3id.org/okn/o/sd#SoftwareImage",
    "baseIri" : "https://w3id.org/okn/o/sd",
    "instances" : 0,
    "label" : {
      "IRI-based" : "SoftwareImage",
      "en" : "Software Image"
    },
    "comment" : {
      "en" : "An image that virtualizes the functionality of a given software. For example, a Docker container."
    },
    "id" : "72",
    "superClasses" : [ "12" ]
  }, {
    "iri" : "http://schema.org/Organization",
    "baseIri" : "http://schema.org",
    "instances" : 0,
    "annotations" : {
      "isDefinedBy" : [ {
        "identifier" : "isDefinedBy",
        "language" : "undefined",
        "value" : "http://schema.org/",
        "type" : "iri"
      } ]
    },
    "label" : {
      "IRI-based" : "Organization"
    },
    "subClasses" : [ "78" ],
    "attributes" : [ "external" ],
    "id" : "79"
  }, {
    "iri" : "http://www.geoscienceontology.org/geo-upper#Variable",
    "baseIri" : "http://www.geoscienceontology.org/geo-upper",
    "instances" : 0,
    "annotations" : {
      "isDefinedBy" : [ {
        "identifier" : "isDefinedBy",
        "language" : "undefined",
        "value" : "http://www.geoscienceontology.org/geo-upper",
        "type" : "iri"
      } ]
    },
    "label" : {
      "IRI-based" : "Variable"
    },
    "attributes" : [ "external" ],
    "id" : "120"
  }, {
    "iri" : "https://w3id.org/okn/o/sd#Software",
    "baseIri" : "https://w3id.org/okn/o/sd",
    "instances" : 0,
    "label" : {
      "IRI-based" : "Software",
      "en" : "Software"
    },
    "subClasses" : [ "72", "7", "32" ],
    "id" : "12",
    "superClasses" : [ "60" ]
  }, {
    "iri" : "https://w3id.org/okn/o/sd#Visualization",
    "baseIri" : "https://w3id.org/okn/o/sd",
    "instances" : 0,
    "label" : {
      "IRI-based" : "Visualization",
      "en" : "Visualization"
    },
    "comment" : {
      "en" : "Class to represent any type of visualization related to a software. For example, a dynamic HTML page, a video, etc."
    },
    "id" : "134"
  }, {
    "iri" : "https://w3id.org/okn/o/sd#StandardVariable",
    "baseIri" : "https://w3id.org/okn/o/sd",
    "instances" : 0,
    "label" : {
      "IRI-based" : "StandardVariable",
      "en" : "Standard Variable"
    },
    "comment" : {
      "en" : "A standard variable, necessary to refer to all the variable using the same nomenclature in a domain ontology. For example, a standard variable may be a SVO variable (http://www.geoscienceontology.org/geo-upper#Variable)"
    },
    "id" : "38",
    "superClasses" : [ "37" ]
  }, {
    "iri" : "http://www.w3.org/2001/XMLSchema#string",
    "baseIri" : "http://www.w3.org/2001/XMLSchema",
    "id" : "74",
    "label" : {
      "IRI-based" : "string"
    }
  }, {
    "iri" : "http://www.w3.org/ns/prov#Activity",
    "baseIri" : "http://www.w3.org/ns/prov",
    "instances" : 0,
    "label" : {
      "IRI-based" : "Activity"
    },
    "subClasses" : [ "44" ],
    "attributes" : [ "external" ],
    "id" : "45"
  }, {
    "iri" : "https://w3id.org/okn/o/sd#ConfigurationSetup",
    "baseIri" : "https://w3id.org/okn/o/sd",
    "instances" : 0,
    "label" : {
      "IRI-based" : "ConfigurationSetup",
      "en" : "Configuration Setup"
    },
    "subClasses" : [ "47" ],
    "comment" : {
      "en" : "Special type of configuration in which some of the inputs or parameters are associated to files or values. A configuration may be associated to multiple setups to facilitate its execution."
    },
    "id" : "41",
    "superClasses" : [ "7" ]
  }, {
    "iri" : "http://www.w3.org/ns/prov#Entity",
    "baseIri" : "http://www.w3.org/ns/prov",
    "instances" : 0,
    "label" : {
      "IRI-based" : "Entity"
    },
    "subClasses" : [ "8" ],
    "attributes" : [ "external" ],
    "id" : "25"
  }, {
    "iri" : "http://www.w3.org/2001/XMLSchema#string",
    "baseIri" : "http://www.w3.org/2001/XMLSchema",
    "id" : "164",
    "label" : {
      "IRI-based" : "string"
    }
  }, {
    "instances" : 0,
    "union" : [ "44", "72", "7" ],
    "attributes" : [ "anonymous", "union" ],
    "id" : "165"
  }, {
    "iri" : "http://www.w3.org/2001/XMLSchema#anyURI",
    "baseIri" : "http://www.w3.org/2001/XMLSchema",
    "id" : "167",
    "label" : {
      "IRI-based" : "anyURI"
    }
  }, {
    "iri" : "http://schema.org/SoftwareSourceCode",
    "baseIri" : "http://schema.org",
    "instances" : 0,
    "label" : {
      "IRI-based" : "SoftwareSourceCode"
    },
    "subClasses" : [ "50" ],
    "attributes" : [ "external" ],
    "id" : "51"
  }, {
    "iri" : "http://www.w3.org/2001/XMLSchema#int",
    "baseIri" : "http://www.w3.org/2001/XMLSchema",
    "id" : "2",
    "label" : {
      "IRI-based" : "int"
    }
  }, {
    "iri" : "http://www.w3.org/2001/XMLSchema#string",
    "baseIri" : "http://www.w3.org/2001/XMLSchema",
    "id" : "28",
    "label" : {
      "IRI-based" : "string"
    }
  }, {
    "iri" : "http://www.w3.org/2001/XMLSchema#anyURI",
    "baseIri" : "http://www.w3.org/2001/XMLSchema",
    "id" : "62",
    "label" : {
      "IRI-based" : "anyURI"
    }
  }, {
    "iri" : "http://www.w3.org/2001/XMLSchema#string",
    "baseIri" : "http://www.w3.org/2001/XMLSchema",
    "id" : "170",
    "label" : {
      "IRI-based" : "string"
    }
  }, {
    "instances" : 0,
    "union" : [ "10", "7" ],
    "attributes" : [ "anonymous", "union" ],
    "id" : "171"
  }, {
    "instances" : 0,
    "union" : [ "10", "69" ],
    "attributes" : [ "anonymous", "union" ],
    "id" : "172"
  }, {
    "iri" : "http://www.w3.org/2001/XMLSchema#string",
    "baseIri" : "http://www.w3.org/2001/XMLSchema",
    "id" : "92",
    "label" : {
      "IRI-based" : "string"
    }
  }, {
    "iri" : "http://www.w3.org/2001/XMLSchema#string",
    "baseIri" : "http://www.w3.org/2001/XMLSchema",
    "id" : "15",
    "label" : {
      "IRI-based" : "string"
    }
  }, {
    "iri" : "http://www.w3.org/2001/XMLSchema#string",
    "baseIri" : "http://www.w3.org/2001/XMLSchema",
    "id" : "101",
    "label" : {
      "IRI-based" : "string"
    }
  }, {
    "iri" : "http://www.w3.org/2001/XMLSchema#anyURI",
    "baseIri" : "http://www.w3.org/2001/XMLSchema",
    "id" : "151",
    "label" : {
      "IRI-based" : "anyURI"
    }
  }, {
    "iri" : "http://www.w3.org/2001/XMLSchema#string",
    "baseIri" : "http://www.w3.org/2001/XMLSchema",
    "id" : "176",
    "label" : {
      "IRI-based" : "string"
    }
  }, {
    "instances" : 0,
    "union" : [ "44", "134", "39", "50", "12", "78", "120", "8", "69", "81", "19", "29" ],
    "attributes" : [ "anonymous", "union" ],
    "id" : "177"
  }, {
    "iri" : "http://www.w3.org/2001/XMLSchema#string",
    "baseIri" : "http://www.w3.org/2001/XMLSchema",
    "id" : "178",
    "label" : {
      "IRI-based" : "string"
    }
  }, {
    "iri" : "http://www.w3.org/2001/XMLSchema#string",
    "baseIri" : "http://www.w3.org/2001/XMLSchema",
    "id" : "179",
    "label" : {
      "IRI-based" : "string"
    }
  }, {
    "iri" : "http://www.w3.org/2001/XMLSchema#string",
    "baseIri" : "http://www.w3.org/2001/XMLSchema",
    "id" : "113",
    "label" : {
      "IRI-based" : "string"
    }
  }, {
    "iri" : "http://www.w3.org/2001/XMLSchema#dateTime",
    "baseIri" : "http://www.w3.org/2001/XMLSchema",
    "id" : "163",
    "label" : {
      "IRI-based" : "dateTime"
    }
  }, {
    "iri" : "http://www.w3.org/2001/XMLSchema#dateTime",
    "baseIri" : "http://www.w3.org/2001/XMLSchema",
    "id" : "103",
    "label" : {
      "IRI-based" : "dateTime"
    }
  }, {
    "iri" : "http://www.w3.org/2001/XMLSchema#string",
    "baseIri" : "http://www.w3.org/2001/XMLSchema",
    "id" : "141",
    "label" : {
      "IRI-based" : "string"
    }
  }, {
    "iri" : "https://w3id.org/okn/o/sd#SampleExecution",
    "baseIri" : "https://w3id.org/okn/o/sd",
    "instances" : 0,
    "label" : {
      "IRI-based" : "SampleExecution",
      "en" : "Sample Execution"
    },
    "comment" : {
      "en" : "A sample execution of a given software"
    },
    "id" : "44",
    "superClasses" : [ "45" ]
  }, {
    "iri" : "http://www.w3.org/2001/XMLSchema#string",
    "baseIri" : "http://www.w3.org/2001/XMLSchema",
    "id" : "185",
    "label" : {
      "IRI-based" : "string"
    }
  }, {
    "iri" : "http://www.w3.org/2001/XMLSchema#string",
    "baseIri" : "http://www.w3.org/2001/XMLSchema",
    "id" : "186",
    "label" : {
      "IRI-based" : "string"
    }
  }, {
    "iri" : "https://w3id.org/okn/o/sd#DatasetSpecification",
    "baseIri" : "https://w3id.org/okn/o/sd",
    "instances" : 0,
    "label" : {
      "IRI-based" : "DatasetSpecification",
      "en" : "Dataset Specification"
    },
    "subClasses" : [ "53" ],
    "comment" : {
      "en" : "Class designed to describe a type of input or output used or produced by a model. For example, Topoflow has several inputs. One of them is a text file with precipitation values. The representation of this input is an instance of a dataset specification."
    },
    "id" : "1",
    "superClasses" : [ "81" ]
  }, {
    "iri" : "https://w3id.org/okn/o/sd#SoftwareVersion",
    "baseIri" : "https://w3id.org/okn/o/sd",
    "instances" : 0,
    "label" : {
      "IRI-based" : "SoftwareVersion",
      "en" : "Software Version"
    },
    "comment" : {
      "en" : "A software version is a specificf type of software that represents a particular set of functionalities. New functionalities and error fixes may occur between software versions"
    },
    "id" : "32",
    "superClasses" : [ "12" ]
  }, {
    "iri" : "http://www.w3.org/2001/XMLSchema#string",
    "baseIri" : "http://www.w3.org/2001/XMLSchema",
    "id" : "194",
    "label" : {
      "IRI-based" : "string"
    }
  }, {
    "iri" : "http://www.w3.org/2001/XMLSchema#string",
    "baseIri" : "http://www.w3.org/2001/XMLSchema",
    "id" : "5",
    "label" : {
      "IRI-based" : "string"
    }
  }, {
    "iri" : "http://www.w3.org/2001/XMLSchema#anyURI",
    "baseIri" : "http://www.w3.org/2001/XMLSchema",
    "id" : "147",
    "label" : {
      "IRI-based" : "anyURI"
    }
  }, {
    "instances" : 0,
    "union" : [ "12", "50" ],
    "attributes" : [ "anonymous", "union" ],
    "id" : "146"
  }, {
    "iri" : "http://www.w3.org/2001/XMLSchema#string",
    "baseIri" : "http://www.w3.org/2001/XMLSchema",
    "id" : "195",
    "label" : {
      "IRI-based" : "string"
    }
  }, {
    "iri" : "http://www.w3.org/2001/XMLSchema#anyURI",
    "baseIri" : "http://www.w3.org/2001/XMLSchema",
    "id" : "196",
    "label" : {
      "IRI-based" : "anyURI"
    }
  }, {
    "instances" : 0,
    "union" : [ "12", "78", "29" ],
    "attributes" : [ "anonymous", "union" ],
    "id" : "4"
  }, {
    "iri" : "http://www.w3.org/2001/XMLSchema#string",
    "baseIri" : "http://www.w3.org/2001/XMLSchema",
    "id" : "33",
    "label" : {
      "IRI-based" : "string"
    }
  }, {
    "iri" : "http://www.w3.org/2001/XMLSchema#anyURI",
    "baseIri" : "http://www.w3.org/2001/XMLSchema",
    "id" : "132",
    "label" : {
      "IRI-based" : "anyURI"
    }
  }, {
    "iri" : "http://www.w3.org/2001/XMLSchema#float",
    "baseIri" : "http://www.w3.org/2001/XMLSchema",
    "id" : "70",
    "label" : {
      "IRI-based" : "float"
    }
  }, {
    "iri" : "http://www.w3.org/2001/XMLSchema#string",
    "baseIri" : "http://www.w3.org/2001/XMLSchema",
    "id" : "67",
    "label" : {
      "IRI-based" : "string"
    }
  }, {
    "iri" : "https://w3id.org/okn/o/sd#DataTransformationSetup",
    "baseIri" : "https://w3id.org/okn/o/sd",
    "instances" : 0,
    "label" : {
      "IRI-based" : "DataTransformationSetup",
      "en" : "Data Transformation Setup"
    },
    "comment" : {
      "en" : "Special type of data transformation where the inputs and parameters have some pre-selected values. For example, they may point to a particular dataset URL to be used in the transformation"
    },
    "id" : "47",
    "superClasses" : [ "36", "41" ]
  }, {
    "instances" : 0,
    "union" : [ "10", "69" ],
    "attributes" : [ "anonymous", "union" ],
    "id" : "159"
  }, {
    "iri" : "http://www.w3.org/2001/XMLSchema#string",
    "baseIri" : "http://www.w3.org/2001/XMLSchema",
    "id" : "175",
    "label" : {
      "IRI-based" : "string"
    }
  }, {
    "iri" : "http://www.w3.org/2001/XMLSchema#string",
    "baseIri" : "http://www.w3.org/2001/XMLSchema",
    "id" : "13",
    "label" : {
      "IRI-based" : "string"
    }
  }, {
    "instances" : 0,
    "union" : [ "10", "69" ],
    "attributes" : [ "anonymous", "union" ],
    "id" : "205"
  }, {
    "iri" : "http://www.w3.org/2001/XMLSchema#string",
    "baseIri" : "http://www.w3.org/2001/XMLSchema",
    "id" : "144",
    "label" : {
      "IRI-based" : "string"
    }
  }, {
    "instances" : 0,
    "union" : [ "134", "1" ],
    "attributes" : [ "anonymous", "union" ],
    "id" : "143"
  }, {
    "iri" : "http://www.w3.org/2001/XMLSchema#string",
    "baseIri" : "http://www.w3.org/2001/XMLSchema",
    "id" : "153",
    "label" : {
      "IRI-based" : "string"
    }
  }, {
    "iri" : "http://www.w3.org/2001/XMLSchema#anyURI",
    "baseIri" : "http://www.w3.org/2001/XMLSchema",
    "id" : "207",
    "label" : {
      "IRI-based" : "anyURI"
    }
  }, {
    "iri" : "http://www.w3.org/2000/01/rdf-schema#Literal",
    "id" : "57",
    "label" : {
      "IRI-based" : "Literal",
      "undefined" : "Literal"
    }
  }, {
    "iri" : "http://www.w3.org/2000/01/rdf-schema#Literal",
    "id" : "55",
    "label" : {
      "IRI-based" : "Literal",
      "undefined" : "Literal"
    }
  }, {
    "iri" : "http://www.w3.org/2000/01/rdf-schema#Literal",
    "id" : "181",
    "label" : {
      "IRI-based" : "Literal",
      "undefined" : "Literal"
    }
  }, {
    "iri" : "http://www.w3.org/2000/01/rdf-schema#Literal",
    "id" : "65",
    "label" : {
      "IRI-based" : "Literal",
      "undefined" : "Literal"
    }
  }, {
    "iri" : "http://www.w3.org/2000/01/rdf-schema#Literal",
    "id" : "22",
    "label" : {
      "IRI-based" : "Literal",
      "undefined" : "Literal"
    }
  }, {
    "iri" : "http://schema.org/Person",
    "baseIri" : "http://schema.org",
    "instances" : 0,
    "annotations" : {
      "isDefinedBy" : [ {
        "identifier" : "isDefinedBy",
        "language" : "undefined",
        "value" : "http://schema.org/",
        "type" : "iri"
      } ]
    },
    "label" : {
      "IRI-based" : "Person"
    },
    "subClasses" : [ "29" ],
    "attributes" : [ "external" ],
    "id" : "30"
  }, {
    "iri" : "https://w3id.org/okn/o/sd#SampleCollection",
    "baseIri" : "https://w3id.org/okn/o/sd",
    "instances" : 0,
    "label" : {
      "IRI-based" : "SampleCollection",
      "en" : "Sample Collection"
    },
    "comment" : {
      "en" : "A collection of resources that are used as sample for running a sfoware component multiple times"
    },
    "id" : "26",
    "superClasses" : [ "8" ]
  }, {
    "iri" : "https://w3id.org/okn/o/sd#FundingInformation",
    "baseIri" : "https://w3id.org/okn/o/sd",
    "instances" : 0,
    "label" : {
      "IRI-based" : "FundingInformation",
      "en" : "Funding Information"
    },
    "comment" : {
      "en" : "A class to represent the funding information of a software project"
    },
    "id" : "117"
  }, {
    "iri" : "http://www.w3.org/2000/01/rdf-schema#Literal",
    "id" : "160",
    "label" : {
      "IRI-based" : "Literal",
      "undefined" : "Literal"
    }
  }, {
    "iri" : "https://w3id.org/okn/o/sd#Parameter",
    "baseIri" : "https://w3id.org/okn/o/sd",
    "instances" : 0,
    "label" : {
      "IRI-based" : "Parameter",
      "en" : "Parameter"
    },
    "comment" : {
      "en" : "A parameter of the model."
    },
    "id" : "69"
  }, {
    "iri" : "http://www.w3.org/2000/01/rdf-schema#Literal",
    "id" : "157",
    "label" : {
      "IRI-based" : "Literal",
      "undefined" : "Literal"
    }
  }, {
    "instances" : 0,
    "union" : [ "12", "78", "29" ],
    "attributes" : [ "anonymous", "union" ],
    "id" : "210"
  }, {
    "instances" : 0,
    "union" : [ "134", "53", "8" ],
    "attributes" : [ "anonymous", "union" ],
    "id" : "136"
  }, {
    "iri" : "http://www.w3.org/2002/07/owl#Thing",
    "baseIri" : "http://owl2vowl.de",
    "id" : "17",
    "label" : {
      "undefined" : "Thing"
    }
  }, {
    "iri" : "http://www.w3.org/2001/XMLSchema#anyURI",
    "baseIri" : "http://www.w3.org/2001/XMLSchema",
    "id" : "211",
    "label" : {
      "IRI-based" : "anyURI"
    }
  }, {
    "iri" : "http://www.w3.org/2001/XMLSchema#string",
    "baseIri" : "http://www.w3.org/2001/XMLSchema",
    "id" : "119",
    "label" : {
      "IRI-based" : "string"
    }
  }, {
    "iri" : "http://www.w3.org/2001/XMLSchema#string",
    "baseIri" : "http://www.w3.org/2001/XMLSchema",
    "id" : "124",
    "label" : {
      "IRI-based" : "string"
    }
  }, {
    "iri" : "http://www.w3.org/2001/XMLSchema#string",
    "baseIri" : "http://www.w3.org/2001/XMLSchema",
    "id" : "223",
    "label" : {
      "IRI-based" : "string"
    }
  }, {
    "instances" : 0,
    "union" : [ "7", "32" ],
    "attributes" : [ "anonymous", "union" ],
    "id" : "224"
  }, {
    "iri" : "http://schema.org/SoftwareApplication",
    "baseIri" : "http://schema.org",
    "instances" : 0,
    "label" : {
      "IRI-based" : "SoftwareApplication"
    },
    "subClasses" : [ "12" ],
    "attributes" : [ "external" ],
    "id" : "60"
  }, {
    "iri" : "http://www.w3.org/2001/XMLSchema#string",
    "baseIri" : "http://www.w3.org/2001/XMLSchema",
    "id" : "122",
    "label" : {
      "IRI-based" : "string"
    }
  }, {
    "iri" : "http://www.w3.org/2001/XMLSchema#float",
    "baseIri" : "http://www.w3.org/2001/XMLSchema",
    "id" : "97",
    "label" : {
      "IRI-based" : "float"
    }
  }, {
    "iri" : "http://www.w3.org/2001/XMLSchema#string",
    "baseIri" : "http://www.w3.org/2001/XMLSchema",
    "id" : "111",
    "label" : {
      "IRI-based" : "string"
    }
  }, {
    "iri" : "http://www.w3.org/2001/XMLSchema#int",
    "baseIri" : "http://www.w3.org/2001/XMLSchema",
    "id" : "222",
    "label" : {
      "IRI-based" : "int"
    }
  }, {
    "instances" : 0,
    "union" : [ "1", "69" ],
    "attributes" : [ "anonymous", "union" ],
    "id" : "221"
  }, {
    "iri" : "http://www.w3.org/2001/XMLSchema#string",
    "baseIri" : "http://www.w3.org/2001/XMLSchema",
    "id" : "95",
    "label" : {
      "IRI-based" : "string"
    }
  }, {
    "iri" : "http://www.w3.org/2001/XMLSchema#string",
    "baseIri" : "http://www.w3.org/2001/XMLSchema",
    "id" : "155",
    "label" : {
      "IRI-based" : "string"
    }
  }, {
    "iri" : "http://www.w3.org/2000/01/rdf-schema#Literal",
    "id" : "237",
    "label" : {
      "IRI-based" : "Literal",
      "undefined" : "Literal"
    }
  }, {
    "iri" : "http://www.w3.org/2000/01/rdf-schema#Literal",
    "id" : "239",
    "label" : {
      "IRI-based" : "Literal",
      "undefined" : "Literal"
    }
  }, {
    "instances" : 0,
    "union" : [ "78", "29" ],
    "attributes" : [ "anonymous", "union" ],
    "id" : "230"
  }, {
    "instances" : 0,
    "union" : [ "1", "69" ],
    "attributes" : [ "anonymous", "union" ],
    "id" : "240"
  }, {
    "instances" : 0,
    "union" : [ "39", "10" ],
    "attributes" : [ "anonymous", "union" ],
    "id" : "183"
  }, {
    "instances" : 0,
    "union" : [ "78", "29" ],
    "attributes" : [ "anonymous", "union" ],
    "id" : "115"
  }, {
    "instances" : 0,
    "union" : [ "10", "69" ],
    "attributes" : [ "anonymous", "union" ],
    "id" : "76"
  }, {
    "iri" : "http://www.w3.org/2001/XMLSchema#string",
    "baseIri" : "http://www.w3.org/2001/XMLSchema",
    "id" : "188",
    "label" : {
      "IRI-based" : "string"
    }
  }, {
    "iri" : "http://www.w3.org/2001/XMLSchema#string",
    "baseIri" : "http://www.w3.org/2001/XMLSchema",
    "id" : "90",
    "label" : {
      "IRI-based" : "string"
    }
  }, {
    "iri" : "http://www.w3.org/2001/XMLSchema#anyURI",
    "baseIri" : "http://www.w3.org/2001/XMLSchema",
    "id" : "243",
    "label" : {
      "IRI-based" : "anyURI"
    }
  }, {
    "iri" : "https://w3id.org/okn/o/sd#DataTransformation",
    "baseIri" : "https://w3id.org/okn/o/sd",
    "instances" : 0,
    "label" : {
      "IRI-based" : "DataTransformation",
      "en" : "Data Transformation"
    },
    "subClasses" : [ "47" ],
    "comment" : {
      "en" : "Class that represents a software for performing data transformation."
    },
    "id" : "36",
    "superClasses" : [ "7" ]
  }, {
    "iri" : "https://w3id.org/okn/o/sd#VariablePresentation",
    "baseIri" : "https://w3id.org/okn/o/sd",
    "instances" : 0,
    "label" : {
      "IRI-based" : "VariablePresentation",
      "en" : "Variable presentation"
    },
    "comment" : {
      "en" : "Concept used to represent an instantiation of a variable in an input/output dataset. For example, a model A may use an input file with temperature expressed in Farenheit (variablePresentation1), while a model B may produce an output with temperature in Celsius (variablePresentation2). Both variable presentations refer to the concept of temperature."
    },
    "id" : "10",
    "superClasses" : [ "37" ]
  }, {
    "instances" : 0,
    "union" : [ "78", "29" ],
    "attributes" : [ "anonymous", "union" ],
    "id" : "85"
  }, {
    "iri" : "https://w3id.org/okn/o/sd#SoftwareConfiguration",
    "baseIri" : "https://w3id.org/okn/o/sd",
    "instances" : 0,
    "label" : {
      "IRI-based" : "SoftwareConfiguration",
      "en" : "Software Configuration"
    },
    "subClasses" : [ "36", "41" ],
    "comment" : {
      "en" : "A software configuration represents a particular way of invoking a function of a software component. A software configuration exposes the precise inputs and outputs that are used for that function. Multiple software configurations may be associated to a software component. A software configuration facilitates the encapsulation of software, and it can be used to represent components of scientific workflows."
    },
    "id" : "7",
    "superClasses" : [ "12" ]
  }, {
    "instances" : 0,
    "union" : [ "134", "53", "12" ],
    "attributes" : [ "anonymous", "union" ],
    "id" : "126"
  }, {
    "iri" : "http://www.w3.org/2000/01/rdf-schema#Literal",
    "id" : "249",
    "label" : {
      "IRI-based" : "Literal",
      "undefined" : "Literal"
    }
  }, {
    "iri" : "http://www.w3.org/2000/01/rdf-schema#Literal",
    "id" : "247",
    "label" : {
      "IRI-based" : "Literal",
      "undefined" : "Literal"
    }
  }, {
    "iri" : "http://www.w3.org/2000/01/rdf-schema#Literal",
    "id" : "251",
    "label" : {
      "IRI-based" : "Literal",
      "undefined" : "Literal"
    }
  }, {
    "iri" : "http://www.w3.org/2000/01/rdf-schema#Literal",
    "id" : "149",
    "label" : {
      "IRI-based" : "Literal",
      "undefined" : "Literal"
    }
  }, {
    "iri" : "http://www.w3.org/2002/07/owl#Thing",
    "baseIri" : "http://owl2vowl.de",
    "id" : "127",
    "label" : {
      "undefined" : "Thing"
    }
  }, {
    "iri" : "http://www.w3.org/2000/01/rdf-schema#Literal",
    "id" : "219",
    "label" : {
      "IRI-based" : "Literal",
      "undefined" : "Literal"
    }
  }, {
    "iri" : "http://www.w3.org/2000/01/rdf-schema#Literal",
    "id" : "137",
    "label" : {
      "IRI-based" : "Literal",
      "undefined" : "Literal"
    }
  }, {
    "iri" : "http://www.w3.org/2000/01/rdf-schema#Literal",
    "id" : "130",
    "label" : {
      "IRI-based" : "Literal",
      "undefined" : "Literal"
    }
  }, {
    "iri" : "https://w3id.org/okn/o/sd#Image",
    "baseIri" : "https://w3id.org/okn/o/sd",
    "instances" : 0,
    "label" : {
      "IRI-based" : "Image",
      "en" : "Image"
    },
    "comment" : {
      "en" : "An image (e.g. tiff file) is a type of dataset specification used to define things like soil, crops, etc."
    },
    "id" : "53",
    "superClasses" : [ "1" ]
  }, {
    "iri" : "https://w3id.org/okn/o/sd#SourceCode",
    "baseIri" : "https://w3id.org/okn/o/sd",
    "instances" : 0,
    "label" : {
      "IRI-based" : "SourceCode",
      "en" : "Source Code"
    },
    "comment" : {
      "en" : "Class representing the characteristics of the code associated with a  software component"
    },
    "id" : "50",
    "superClasses" : [ "51" ]
  }, {
    "iri" : "http://www.w3.org/2000/01/rdf-schema#Literal",
    "id" : "217",
    "label" : {
      "IRI-based" : "Literal",
      "undefined" : "Literal"
    }
  }, {
    "iri" : "https://w3id.org/okn/o/sd#Organization",
    "baseIri" : "https://w3id.org/okn/o/sd",
    "instances" : 0,
    "label" : {
      "IRI-based" : "Organization",
      "en" : "Organization"
    },
    "comment" : {
      "en" : "An organized ody of people with a particular purpose"
    },
    "id" : "78",
    "superClasses" : [ "79" ]
  }, {
    "iri" : "http://www.w3.org/2000/01/rdf-schema#Literal",
    "id" : "215",
    "label" : {
      "IRI-based" : "Literal",
      "undefined" : "Literal"
    }
  }, {
    "iri" : "http://www.w3.org/2002/07/owl#Thing",
    "baseIri" : "http://owl2vowl.de",
    "id" : "106",
    "label" : {
      "undefined" : "Thing"
    }
  }, {
    "iri" : "http://www.w3.org/2000/01/rdf-schema#Literal",
    "id" : "192",
    "label" : {
      "IRI-based" : "Literal",
      "undefined" : "Literal"
    }
  }, {
    "iri" : "http://www.w3.org/2000/01/rdf-schema#Literal",
    "id" : "88",
    "label" : {
      "IRI-based" : "Literal",
      "undefined" : "Literal"
    }
  }, {
    "iri" : "http://www.w3.org/2000/01/rdf-schema#Literal",
    "id" : "201",
    "label" : {
      "IRI-based" : "Literal",
      "undefined" : "Literal"
    }
  }, {
    "iri" : "http://www.w3.org/2000/01/rdf-schema#Literal",
    "id" : "199",
    "label" : {
      "IRI-based" : "Literal",
      "undefined" : "Literal"
    }
  } ],
  "property" : [ {
    "id" : "0",
    "type" : "owl:datatypeProperty"
  }, {
    "id" : "3",
    "type" : "owl:datatypeProperty"
  }, {
    "id" : "6",
    "type" : "owl:objectProperty"
  }, {
    "id" : "9",
    "type" : "owl:objectProperty"
  }, {
    "id" : "11",
    "type" : "owl:datatypeProperty"
  }, {
    "id" : "14",
    "type" : "owl:datatypeProperty"
  }, {
    "id" : "16",
    "type" : "owl:objectProperty"
  }, {
    "id" : "21",
    "type" : "owl:datatypeProperty"
  }, {
    "id" : "23",
    "type" : "owl:objectProperty"
  }, {
    "id" : "27",
    "type" : "owl:datatypeProperty"
  }, {
    "id" : "31",
    "type" : "owl:datatypeProperty"
  }, {
    "id" : "34",
    "type" : "owl:objectProperty"
  }, {
    "id" : "35",
    "type" : "rdfs:SubClassOf"
  }, {
    "id" : "40",
    "type" : "rdfs:SubClassOf"
  }, {
    "id" : "42",
    "type" : "rdfs:SubClassOf"
  }, {
    "id" : "43",
    "type" : "rdfs:SubClassOf"
  }, {
    "id" : "46",
    "type" : "rdfs:SubClassOf"
  }, {
    "id" : "48",
    "type" : "rdfs:SubClassOf"
  }, {
    "id" : "49",
    "type" : "rdfs:SubClassOf"
  }, {
    "id" : "52",
    "type" : "rdfs:SubClassOf"
  }, {
    "id" : "54",
    "type" : "owl:datatypeProperty"
  }, {
    "id" : "56",
    "type" : "owl:datatypeProperty"
  }, {
    "id" : "58",
    "type" : "rdfs:SubClassOf"
  }, {
    "id" : "59",
    "type" : "rdfs:SubClassOf"
  }, {
    "id" : "61",
    "type" : "owl:datatypeProperty"
  }, {
    "id" : "63",
    "type" : "rdfs:SubClassOf"
  }, {
    "id" : "64",
    "type" : "owl:datatypeProperty"
  }, {
    "id" : "66",
    "type" : "owl:datatypeProperty"
  }, {
    "id" : "68",
    "type" : "owl:datatypeProperty"
  }, {
    "id" : "71",
    "type" : "owl:objectProperty"
  }, {
    "id" : "73",
    "type" : "owl:datatypeProperty"
  }, {
    "id" : "75",
    "type" : "owl:objectProperty"
  }, {
    "id" : "77",
    "type" : "rdfs:SubClassOf"
  }, {
    "id" : "80",
    "type" : "rdfs:SubClassOf"
  }, {
    "id" : "82",
    "type" : "rdfs:SubClassOf"
  }, {
    "id" : "83",
    "type" : "rdfs:SubClassOf"
  }, {
    "id" : "84",
    "type" : "owl:objectProperty"
  }, {
    "id" : "87",
    "type" : "owl:datatypeProperty"
  }, {
    "id" : "89",
    "type" : "owl:datatypeProperty"
  }, {
    "id" : "91",
    "type" : "owl:datatypeProperty"
  }, {
    "id" : "93",
    "type" : "owl:objectProperty"
  }, {
    "id" : "94",
    "type" : "owl:datatypeProperty"
  }, {
    "id" : "96",
    "type" : "owl:datatypeProperty"
  }, {
    "id" : "98",
    "type" : "owl:objectProperty"
  }, {
    "id" : "100",
    "type" : "owl:datatypeProperty"
  }, {
    "id" : "102",
    "type" : "owl:datatypeProperty"
  }, {
    "id" : "104",
    "type" : "owl:objectProperty"
  }, {
    "id" : "105",
    "type" : "owl:objectProperty"
  }, {
    "id" : "107",
    "type" : "owl:objectProperty"
  }, {
    "id" : "109",
    "type" : "owl:objectProperty"
  }, {
    "id" : "110",
    "type" : "owl:datatypeProperty"
  }, {
    "id" : "112",
    "type" : "owl:datatypeProperty"
  }, {
    "id" : "114",
    "type" : "owl:objectProperty"
  }, {
    "id" : "24",
    "type" : "owl:objectProperty"
  }, {
    "id" : "118",
    "type" : "owl:datatypeProperty"
  }, {
    "id" : "121",
    "type" : "owl:datatypeProperty"
  }, {
    "id" : "123",
    "type" : "owl:datatypeProperty"
  }, {
    "id" : "125",
    "type" : "owl:objectProperty"
  }, {
    "id" : "18",
    "type" : "owl:objectProperty"
  }, {
    "id" : "129",
    "type" : "owl:datatypeProperty"
  }, {
    "id" : "131",
    "type" : "owl:datatypeProperty"
  }, {
    "id" : "133",
    "type" : "owl:objectProperty"
  }, {
    "id" : "135",
    "type" : "owl:datatypeProperty"
  }, {
    "id" : "138",
    "type" : "owl:objectProperty"
  }, {
    "id" : "140",
    "type" : "owl:datatypeProperty"
  }, {
    "id" : "142",
    "type" : "owl:datatypeProperty"
  }, {
    "id" : "145",
    "type" : "owl:datatypeProperty"
  }, {
    "id" : "148",
    "type" : "owl:datatypeProperty"
  }, {
    "id" : "150",
    "type" : "owl:datatypeProperty"
  }, {
    "id" : "152",
    "type" : "owl:datatypeProperty"
  }, {
    "id" : "108",
    "type" : "owl:objectProperty"
  }, {
    "id" : "154",
    "type" : "owl:datatypeProperty"
  }, {
    "id" : "156",
    "type" : "owl:datatypeProperty"
  }, {
    "id" : "158",
    "type" : "owl:datatypeProperty"
  }, {
    "id" : "161",
    "type" : "owl:objectProperty"
  }, {
    "id" : "162",
    "type" : "owl:datatypeProperty"
  }, {
    "id" : "166",
    "type" : "owl:objectProperty"
  }, {
    "id" : "168",
    "type" : "owl:objectProperty"
  }, {
    "id" : "169",
    "type" : "owl:objectProperty"
  }, {
    "id" : "99",
    "type" : "owl:objectProperty"
  }, {
    "id" : "173",
    "type" : "owl:datatypeProperty"
  }, {
    "id" : "174",
    "type" : "owl:datatypeProperty"
  }, {
    "id" : "116",
    "type" : "owl:objectProperty"
  }, {
    "id" : "180",
    "type" : "owl:datatypeProperty"
  }, {
    "id" : "182",
    "type" : "owl:objectProperty"
  }, {
    "id" : "184",
    "type" : "owl:datatypeProperty"
  }, {
    "id" : "128",
    "type" : "owl:objectProperty"
  }, {
    "id" : "187",
    "type" : "owl:datatypeProperty"
  }, {
    "id" : "86",
    "type" : "owl:objectProperty"
  }, {
    "id" : "189",
    "type" : "owl:objectProperty"
  }, {
    "id" : "190",
    "type" : "owl:objectProperty"
  }, {
    "id" : "191",
    "type" : "owl:datatypeProperty"
  }, {
    "id" : "193",
    "type" : "owl:datatypeProperty"
  }, {
    "id" : "197",
    "type" : "owl:objectProperty"
  }, {
    "id" : "198",
    "type" : "owl:datatypeProperty"
  }, {
    "id" : "200",
    "type" : "owl:datatypeProperty"
  }, {
    "id" : "202",
    "type" : "owl:objectProperty"
  }, {
    "id" : "204",
    "type" : "owl:datatypeProperty"
  }, {
    "id" : "206",
    "type" : "owl:datatypeProperty"
  }, {
    "id" : "208",
    "type" : "owl:objectProperty"
  }, {
    "id" : "209",
    "type" : "owl:datatypeProperty"
  }, {
    "id" : "212",
    "type" : "owl:objectProperty"
  }, {
    "id" : "213",
    "type" : "owl:datatypeProperty"
  }, {
    "id" : "214",
    "type" : "owl:datatypeProperty"
  }, {
    "id" : "216",
    "type" : "owl:datatypeProperty"
  }, {
    "id" : "218",
    "type" : "owl:datatypeProperty"
  }, {
    "id" : "220",
    "type" : "owl:datatypeProperty"
  }, {
    "id" : "225",
    "type" : "owl:objectProperty"
  }, {
    "id" : "226",
    "type" : "owl:objectProperty"
  }, {
    "id" : "228",
    "type" : "owl:datatypeProperty"
  }, {
    "id" : "229",
    "type" : "owl:objectProperty"
  }, {
    "id" : "231",
    "type" : "owl:datatypeProperty"
  }, {
    "id" : "232",
    "type" : "rdfs:SubClassOf"
  }, {
    "id" : "233",
    "type" : "owl:objectProperty"
  }, {
    "id" : "234",
    "type" : "rdfs:SubClassOf"
  }, {
    "id" : "235",
    "type" : "rdfs:SubClassOf"
  }, {
    "id" : "236",
    "type" : "rdfs:SubClassOf"
  }, {
    "id" : "238",
    "type" : "rdfs:SubClassOf"
  }, {
    "id" : "241",
    "type" : "owl:datatypeProperty"
  }, {
    "id" : "242",
    "type" : "owl:objectProperty"
  }, {
    "id" : "244",
    "type" : "owl:datatypeProperty"
  }, {
    "id" : "245",
    "type" : "owl:objectProperty"
  }, {
    "id" : "203",
    "type" : "owl:objectProperty"
  }, {
    "id" : "246",
    "type" : "owl:datatypeProperty"
  }, {
    "id" : "248",
    "type" : "owl:datatypeProperty"
  }, {
    "id" : "250",
    "type" : "owl:datatypeProperty"
  }, {
    "id" : "252",
    "type" : "owl:objectProperty"
  }, {
    "id" : "253",
    "type" : "owl:datatypeProperty"
  }, {
    "id" : "254",
    "type" : "owl:datatypeProperty"
  }, {
    "id" : "139",
    "type" : "owl:objectProperty"
  }, {
    "id" : "227",
    "type" : "owl:objectProperty"
  }, {
    "id" : "255",
    "type" : "owl:datatypeProperty"
  }, {
    "id" : "256",
    "type" : "owl:datatypeProperty"
  }, {
    "id" : "257",
    "type" : "owl:datatypeProperty"
  }, {
    "id" : "258",
    "type" : "owl:datatypeProperty"
  }, {
    "id" : "259",
    "type" : "owl:objectProperty"
  } ],
  "propertyAttribute" : [ {
    "iri" : "https://w3id.org/okn/o/sd#hasDimensionality",
    "baseIri" : "https://w3id.org/okn/o/sd",
    "range" : "2",
    "label" : {
      "IRI-based" : "hasDimensionality",
      "en" : "has dimensionality"
    },
    "domain" : "1",
    "comment" : {
      "en" : "Property to indicate dimensionality of the input or output of a dataset specification"
    },
    "attributes" : [ "datatype" ],
    "id" : "0"
  }, {
    "iri" : "https://w3id.org/okn/o/sd#identifier",
    "baseIri" : "https://w3id.org/okn/o/sd",
    "range" : "5",
    "label" : {
      "IRI-based" : "identifier",
      "en" : "identifier"
    },
    "domain" : "4",
    "comment" : {
      "en" : "Identifier of the resource being described"
    },
    "attributes" : [ "datatype" ],
    "id" : "3"
  }, {
    "iri" : "https://w3id.org/okn/o/sd#hasSampleResult",
    "baseIri" : "https://w3id.org/okn/o/sd",
    "range" : "8",
    "label" : {
      "IRI-based" : "hasSampleResult",
      "en" : "has sample result"
    },
    "domain" : "7",
    "attributes" : [ "object" ],
    "id" : "6"
  }, {
    "iri" : "https://w3id.org/okn/o/sd#partOfDataset",
    "baseIri" : "https://w3id.org/okn/o/sd",
    "range" : "1",
    "label" : {
      "IRI-based" : "partOfDataset",
      "en" : "part of dataset"
    },
    "domain" : "10",
    "comment" : {
      "en" : "Associates a presentation with a dataset where the presentation occurs"
    },
    "attributes" : [ "object" ],
    "id" : "9"
  }, {
    "iri" : "https://w3id.org/okn/o/sd#hasPurpose",
    "baseIri" : "https://w3id.org/okn/o/sd",
    "range" : "13",
    "label" : {
      "IRI-based" : "hasPurpose",
      "en" : "has purpose"
    },
    "domain" : "12",
    "comment" : {
      "en" : "Objective or main functionality that can be achieved by running this software"
    },
    "attributes" : [ "datatype" ],
    "id" : "11"
  }, {
    "iri" : "https://w3id.org/okn/o/sd#hasAssumption",
    "baseIri" : "https://w3id.org/okn/o/sd",
    "range" : "15",
    "label" : {
      "IRI-based" : "hasAssumption",
      "en" : "has assumption"
    },
    "domain" : "12",
    "comment" : {
      "en" : "Assumptions of a software, e.g. the solver being used for a particular model, the source of the data (e.g., all data must have a given resolution), etc."
    },
    "attributes" : [ "datatype" ],
    "id" : "14"
  }, {
    "iri" : "http://schema.org/copyrightYear",
    "baseIri" : "http://schema.org",
    "range" : "17",
    "annotations" : {
      "isDefinedBy" : [ {
        "identifier" : "isDefinedBy",
        "language" : "undefined",
        "value" : "http://schema.org/",
        "type" : "iri"
      } ]
    },
    "label" : {
      "IRI-based" : "copyrightYear"
    },
    "domain" : "17",
    "subproperty" : [ "18" ],
    "attributes" : [ "external", "object" ],
    "id" : "16"
  }, {
    "iri" : "http://schema.org/programmingLanguage",
    "baseIri" : "http://schema.org",
    "range" : "22",
    "annotations" : {
      "isDefinedBy" : [ {
        "identifier" : "isDefinedBy",
        "language" : "undefined",
        "value" : "http://schema.org/",
        "type" : "iri"
      } ]
    },
    "label" : {
      "IRI-based" : "programmingLanguage"
    },
    "domain" : "17",
    "attributes" : [ "external", "datatype" ],
    "id" : "21"
  }, {
    "iri" : "http://www.w3.org/2002/07/owl#topObjectProperty",
    "baseIri" : "http://www.w3.org/2002/07/owl",
    "range" : "17",
    "label" : {
      "IRI-based" : "topObjectProperty"
    },
    "domain" : "17",
    "subproperty" : [ "24" ],
    "attributes" : [ "external", "object" ],
    "id" : "23"
  }, {
    "iri" : "https://w3id.org/okn/o/sd#hasExample",
    "baseIri" : "https://w3id.org/okn/o/sd",
    "range" : "28",
    "label" : {
      "IRI-based" : "hasExample",
      "en" : "has example"
    },
    "domain" : "12",
    "comment" : {
      "en" : "An example explaining a scenario where the model was used in plain language."
    },
    "attributes" : [ "datatype" ],
    "id" : "27"
  }, {
    "iri" : "https://w3id.org/okn/o/sd#hasVersionId",
    "baseIri" : "https://w3id.org/okn/o/sd",
    "range" : "33",
    "label" : {
      "IRI-based" : "hasVersionId",
      "en" : "has version id"
    },
    "domain" : "32",
    "comment" : {
      "en" : "Identifier of the version of this software"
    },
    "attributes" : [ "datatype" ],
    "id" : "31"
  }, {
    "iri" : "https://w3id.org/okn/o/sd#hasOutput",
    "baseIri" : "https://w3id.org/okn/o/sd",
    "range" : "1",
    "label" : {
      "IRI-based" : "hasOutput",
      "en" : "has output"
    },
    "domain" : "7",
    "comment" : {
      "en" : "Property that expresses what are the outputs of a model"
    },
    "attributes" : [ "object" ],
    "id" : "34"
  }, {
    "range" : "7",
    "domain" : "36",
    "attributes" : [ "anonymous", "object" ],
    "id" : "35"
  }, {
    "range" : "7",
    "domain" : "41",
    "attributes" : [ "anonymous", "object" ],
    "id" : "40"
  }, {
    "range" : "12",
    "domain" : "32",
    "attributes" : [ "anonymous", "object" ],
    "id" : "42"
  }, {
    "range" : "45",
    "domain" : "44",
    "attributes" : [ "anonymous", "object" ],
    "id" : "43"
  }, {
    "range" : "41",
    "domain" : "47",
    "attributes" : [ "anonymous", "object" ],
    "id" : "46"
  }, {
    "range" : "25",
    "domain" : "8",
    "attributes" : [ "anonymous", "object" ],
    "id" : "48"
  }, {
    "range" : "51",
    "domain" : "50",
    "attributes" : [ "anonymous", "object" ],
    "id" : "49"
  }, {
    "range" : "1",
    "domain" : "53",
    "attributes" : [ "anonymous", "object" ],
    "id" : "52"
  }, {
    "iri" : "http://schema.org/codeRepository",
    "baseIri" : "http://schema.org",
    "range" : "55",
    "annotations" : {
      "isDefinedBy" : [ {
        "identifier" : "isDefinedBy",
        "language" : "undefined",
        "value" : "http://schema.org/",
        "type" : "iri"
      } ]
    },
    "label" : {
      "IRI-based" : "codeRepository"
    },
    "domain" : "17",
    "attributes" : [ "external", "datatype" ],
    "id" : "54"
  }, {
    "iri" : "http://schema.org/description",
    "baseIri" : "http://schema.org",
    "range" : "57",
    "annotations" : {
      "isDefinedBy" : [ {
        "identifier" : "isDefinedBy",
        "language" : "undefined",
        "value" : "http://schema.org/",
        "type" : "iri"
      } ]
    },
    "label" : {
      "IRI-based" : "description"
    },
    "domain" : "17",
    "attributes" : [ "external", "datatype" ],
    "id" : "56"
  }, {
    "range" : "30",
    "domain" : "29",
    "attributes" : [ "anonymous", "object" ],
    "id" : "58"
  }, {
    "range" : "60",
    "domain" : "12",
    "attributes" : [ "anonymous", "object" ],
    "id" : "59"
  }, {
    "iri" : "https://w3id.org/okn/o/sd#hasDownloadURL",
    "baseIri" : "https://w3id.org/okn/o/sd",
    "range" : "62",
    "label" : {
      "IRI-based" : "hasDownloadURL",
      "en" : "has download URL"
    },
    "domain" : "12",
    "comment" : {
      "en" : "Download URL where to obtain the source/executable of the software"
    },
    "attributes" : [ "datatype" ],
    "id" : "61"
  }, {
    "range" : "36",
    "domain" : "47",
    "attributes" : [ "anonymous", "object" ],
    "id" : "63"
  }, {
    "iri" : "http://schema.org/keywords",
    "baseIri" : "http://schema.org",
    "range" : "65",
    "annotations" : {
      "isDefinedBy" : [ {
        "identifier" : "isDefinedBy",
        "language" : "undefined",
        "value" : "http://schema.org/",
        "type" : "iri"
      } ]
    },
    "label" : {
      "IRI-based" : "keywords"
    },
    "domain" : "17",
    "attributes" : [ "external", "datatype" ],
    "id" : "64"
  }, {
    "iri" : "https://w3id.org/okn/o/sd#hasShortName",
    "baseIri" : "https://w3id.org/okn/o/sd",
    "range" : "67",
    "label" : {
      "IRI-based" : "hasShortName",
      "en" : "has short name"
    },
    "domain" : "10",
    "comment" : {
      "en" : "A short name (e.g., temperature) capturing the high-level concept of the variable"
    },
    "attributes" : [ "datatype" ],
    "id" : "66"
  }, {
    "iri" : "https://w3id.org/okn/o/sd#hasStepSize",
    "baseIri" : "https://w3id.org/okn/o/sd",
    "range" : "70",
    "label" : {
      "IRI-based" : "hasStepSize",
      "en" : "has step size"
    },
    "domain" : "69",
    "comment" : {
      "en" : "Property that determines what are the increments (step size) that are commonly used to vary a parameter. This is commonly used for automatically setting up software tests. For example, if I want to set up a model and try 30 reasonable values on a parameter, I may use the default value and the step size to create the appropriate increments. If the step size is 0.1 and the default value is 0, then I will will be able to create setups: 0, 0.1, 0.2...2.9,3"
    },
    "attributes" : [ "datatype" ],
    "id" : "68"
  }, {
    "iri" : "https://w3id.org/okn/o/sd#hasSoftwareImage",
    "baseIri" : "https://w3id.org/okn/o/sd",
    "range" : "72",
    "label" : {
      "IRI-based" : "hasSoftwareImage",
      "en" : "has software image"
    },
    "domain" : "7",
    "comment" : {
      "en" : "Function to link a function with its corresponding container"
    },
    "attributes" : [ "functional", "object" ],
    "id" : "71"
  }, {
    "iri" : "https://w3id.org/okn/o/sd#hasFAQ",
    "baseIri" : "https://w3id.org/okn/o/sd",
    "range" : "74",
    "label" : {
      "IRI-based" : "hasFAQ",
      "en" : "has FAQ"
    },
    "domain" : "12",
    "comment" : {
      "en" : "Frequently asked questions about a software"
    },
    "attributes" : [ "datatype" ],
    "id" : "73"
  }, {
    "iri" : "https://w3id.org/okn/o/sd#usesUnit",
    "baseIri" : "https://w3id.org/okn/o/sd",
    "range" : "19",
    "label" : {
      "IRI-based" : "usesUnit",
      "en" : "uses unit"
    },
    "domain" : "76",
    "comment" : {
      "en" : "Property used to link a variable presentation or time interval to the unit they are represented in"
    },
    "attributes" : [ "functional", "object" ],
    "id" : "75"
  }, {
    "range" : "79",
    "domain" : "78",
    "attributes" : [ "anonymous", "object" ],
    "id" : "77"
  }, {
    "range" : "81",
    "domain" : "1",
    "attributes" : [ "anonymous", "object" ],
    "id" : "80"
  }, {
    "range" : "12",
    "domain" : "72",
    "attributes" : [ "anonymous", "object" ],
    "id" : "82"
  }, {
    "range" : "12",
    "domain" : "7",
    "attributes" : [ "anonymous", "object" ],
    "id" : "83"
  }, {
    "iri" : "https://w3id.org/okn/o/sd#author",
    "baseIri" : "https://w3id.org/okn/o/sd",
    "range" : "85",
    "label" : {
      "IRI-based" : "author",
      "en" : "author"
    },
    "superproperty" : [ "86" ],
    "domain" : "12",
    "attributes" : [ "object" ],
    "id" : "84"
  }, {
    "iri" : "http://www.w3.org/ns/prov#value",
    "baseIri" : "http://www.w3.org/ns/prov",
    "range" : "88",
    "annotations" : {
      "isDefinedBy" : [ {
        "identifier" : "isDefinedBy",
        "language" : "undefined",
        "value" : "http://www.w3.org/ns/prov#",
        "type" : "iri"
      } ]
    },
    "label" : {
      "IRI-based" : "value"
    },
    "domain" : "17",
    "attributes" : [ "external", "datatype" ],
    "id" : "87"
  }, {
    "iri" : "https://w3id.org/okn/o/sd#citation",
    "baseIri" : "https://w3id.org/okn/o/sd",
    "range" : "90",
    "label" : {
      "IRI-based" : "citation",
      "en" : "citation"
    },
    "domain" : "12",
    "comment" : {
      "en" : "How to cite this software"
    },
    "attributes" : [ "datatype" ],
    "id" : "89"
  }, {
    "iri" : "https://w3id.org/okn/o/sd#hasDataType",
    "baseIri" : "https://w3id.org/okn/o/sd",
    "range" : "92",
    "label" : {
      "IRI-based" : "hasDataType",
      "en" : "has data type"
    },
    "domain" : "69",
    "comment" : {
      "en" : "Property that indicates the data type of a parameter"
    },
    "attributes" : [ "datatype" ],
    "id" : "91"
  }, {
    "iri" : "https://w3id.org/okn/o/sd#hasVersion",
    "baseIri" : "https://w3id.org/okn/o/sd",
    "range" : "32",
    "label" : {
      "IRI-based" : "hasVersion",
      "en" : "has software version"
    },
    "domain" : "12",
    "attributes" : [ "object" ],
    "id" : "93"
  }, {
    "iri" : "https://w3id.org/okn/o/sd#programmingLanguage",
    "baseIri" : "https://w3id.org/okn/o/sd",
    "range" : "95",
    "label" : {
      "IRI-based" : "programmingLanguage",
      "en" : "programming language"
    },
    "domain" : "50",
    "attributes" : [ "datatype" ],
    "id" : "94"
  }, {
    "iri" : "https://w3id.org/okn/o/sd#recommendedIncrement",
    "baseIri" : "https://w3id.org/okn/o/sd",
    "range" : "97",
    "label" : {
      "IRI-based" : "recommendedIncrement",
      "en" : "recommended increment"
    },
    "domain" : "69",
    "comment" : {
      "en" : "Value that represents how a parameter should be incremented on each iteration of a software component execution. This value is important when preparing execution ensembles automatically, e.g., simulating crop production varying the parameter \"fertilizer amount\" in increments of 10%."
    },
    "attributes" : [ "datatype" ],
    "id" : "96"
  }, {
    "iri" : "http://schema.org/screenshot",
    "baseIri" : "http://schema.org",
    "range" : "17",
    "annotations" : {
      "isDefinedBy" : [ {
        "identifier" : "isDefinedBy",
        "language" : "undefined",
        "value" : "http://schema.org/",
        "type" : "iri"
      } ]
    },
    "label" : {
      "IRI-based" : "screenshot"
    },
    "domain" : "17",
    "subproperty" : [ "99" ],
    "attributes" : [ "external", "object" ],
    "id" : "98"
  }, {
    "iri" : "https://w3id.org/okn/o/sd#hasAcceptedValues",
    "baseIri" : "https://w3id.org/okn/o/sd",
    "range" : "101",
    "label" : {
      "IRI-based" : "hasAcceptedValues",
      "en" : "has accepted values"
    },
    "domain" : "69",
    "comment" : {
      "en" : "Property that constraints which values are accepted for a parameter. For example, the name of a crop can only be \"Maize\" or \"Sorghum\""
    },
    "attributes" : [ "datatype" ],
    "id" : "100"
  }, {
    "iri" : "https://w3id.org/okn/o/sd#dateCreated",
    "baseIri" : "https://w3id.org/okn/o/sd",
    "range" : "103",
    "label" : {
      "IRI-based" : "dateCreated",
      "en" : "date created"
    },
    "domain" : "12",
    "attributes" : [ "datatype" ],
    "id" : "102"
  }, {
    "iri" : "https://w3id.org/okn/o/sd#logo",
    "baseIri" : "https://w3id.org/okn/o/sd",
    "range" : "53",
    "label" : {
      "IRI-based" : "logo"
    },
    "domain" : "12",
    "attributes" : [ "object" ],
    "id" : "104"
  }, {
    "iri" : "https://w3id.org/okn/o/sd#hasFileStructure",
    "baseIri" : "https://w3id.org/okn/o/sd",
    "range" : "106",
    "label" : {
      "IRI-based" : "hasFileStructure",
      "en" : "has file structure"
    },
    "domain" : "1",
    "comment" : {
      "en" : "Relates a dataset specification to the data structure definition"
    },
    "attributes" : [ "functional", "object" ],
    "id" : "105"
  }, {
    "iri" : "http://www.w3.org/ns/prov#wasDerivedFrom",
    "baseIri" : "http://www.w3.org/ns/prov",
    "range" : "17",
    "annotations" : {
      "isDefinedBy" : [ {
        "identifier" : "isDefinedBy",
        "language" : "undefined",
        "value" : "http://www.w3.org/ns/prov#",
        "type" : "iri"
      } ]
    },
    "label" : {
      "IRI-based" : "wasDerivedFrom"
    },
    "domain" : "17",
    "subproperty" : [ "108" ],
    "attributes" : [ "external", "object" ],
    "id" : "107"
  }, {
    "iri" : "https://w3id.org/okn/o/sd#adjustableParameter",
    "baseIri" : "https://w3id.org/okn/o/sd",
    "range" : "69",
    "label" : {
      "IRI-based" : "adjustableParameter",
      "en" : "adjustable parameter"
    },
    "domain" : "41",
    "comment" : {
      "en" : "Parameter that can be adjusted in a configuration setup"
    },
    "attributes" : [ "object" ],
    "id" : "109"
  }, {
    "iri" : "https://w3id.org/okn/o/sd#shortDescription",
    "baseIri" : "https://w3id.org/okn/o/sd",
    "range" : "111",
    "label" : {
      "IRI-based" : "shortDescription",
      "undefined" : "short description"
    },
    "domain" : "12",
    "comment" : {
      "en" : "A summarized description of the resource"
    },
    "attributes" : [ "datatype" ],
    "id" : "110"
  }, {
    "iri" : "https://w3id.org/okn/o/sd#dataCatalogIdentifier",
    "baseIri" : "https://w3id.org/okn/o/sd",
    "range" : "113",
    "label" : {
      "IRI-based" : "dataCatalogIdentifier",
      "en" : "data catalog identifier"
    },
    "domain" : "8",
    "comment" : {
      "en" : "An identifier for resources with metadata entries in a data catalog"
    },
    "attributes" : [ "datatype" ],
    "id" : "112"
  }, {
    "iri" : "https://w3id.org/okn/o/sd#publisher",
    "baseIri" : "https://w3id.org/okn/o/sd",
    "range" : "115",
    "label" : {
      "IRI-based" : "publisher",
      "en" : "publisher"
    },
    "superproperty" : [ "116" ],
    "domain" : "12",
    "attributes" : [ "object" ],
    "id" : "114"
  }, {
    "iri" : "https://w3id.org/okn/o/sd#fundingSource",
    "baseIri" : "https://w3id.org/okn/o/sd",
    "range" : "78",
    "label" : {
      "IRI-based" : "fundingSource",
      "en" : "funding source"
    },
    "superproperty" : [ "23" ],
    "domain" : "117",
    "attributes" : [ "object" ],
    "id" : "24"
  }, {
    "iri" : "https://w3id.org/okn/o/sd#supportDetails",
    "baseIri" : "https://w3id.org/okn/o/sd",
    "range" : "119",
    "label" : {
      "IRI-based" : "supportDetails",
      "en" : "support details"
    },
    "domain" : "12",
    "comment" : {
      "en" : "Property to link details, such as mailing lists in case a contact person is not provided"
    },
    "attributes" : [ "datatype" ],
    "id" : "118"
  }, {
    "iri" : "https://w3id.org/okn/o/sd#referencePublication",
    "baseIri" : "https://w3id.org/okn/o/sd",
    "range" : "122",
    "label" : {
      "IRI-based" : "referencePublication",
      "en" : "reference publication"
    },
    "domain" : "12",
    "comment" : {
      "en" : "Main publication to cite in this software"
    },
    "attributes" : [ "datatype" ],
    "id" : "121"
  }, {
    "iri" : "https://w3id.org/okn/o/sd#softwareRequirements",
    "baseIri" : "https://w3id.org/okn/o/sd",
    "range" : "124",
    "label" : {
      "IRI-based" : "softwareRequirements",
      "en" : "software requirements"
    },
    "domain" : "12",
    "attributes" : [ "datatype" ],
    "id" : "123"
  }, {
    "iri" : "https://w3id.org/okn/o/sd#hadPrimarySource",
    "baseIri" : "https://w3id.org/okn/o/sd",
    "range" : "127",
    "label" : {
      "IRI-based" : "hadPrimarySource"
    },
    "superproperty" : [ "128" ],
    "domain" : "126",
    "comment" : {
      "en" : "had primary source"
    },
    "attributes" : [ "object" ],
    "id" : "125"
  }, {
    "iri" : "https://w3id.org/okn/o/sd#copyrightYear",
    "baseIri" : "https://w3id.org/okn/o/sd",
    "range" : "17",
    "label" : {
      "IRI-based" : "copyrightYear",
      "en" : "copyright year"
    },
    "superproperty" : [ "16" ],
    "domain" : "17",
    "attributes" : [ "object" ],
    "id" : "18"
  }, {
    "iri" : "http://schema.org/name",
    "baseIri" : "http://schema.org",
    "range" : "130",
    "annotations" : {
      "isDefinedBy" : [ {
        "identifier" : "isDefinedBy",
        "language" : "undefined",
        "value" : "http://schema.org/",
        "type" : "iri"
      } ]
    },
    "label" : {
      "IRI-based" : "name"
    },
    "domain" : "17",
    "attributes" : [ "external", "datatype" ],
    "id" : "129"
  }, {
    "iri" : "https://w3id.org/okn/o/sd#hasSupportScriptLocation",
    "baseIri" : "https://w3id.org/okn/o/sd",
    "range" : "132",
    "label" : {
      "IRI-based" : "hasSupportScriptLocation",
      "en" : "has support script location"
    },
    "domain" : "7",
    "comment" : {
      "en" : "Property that links to the location of scripts that may be used from the main runnable script."
    },
    "attributes" : [ "datatype" ],
    "id" : "131"
  }, {
    "iri" : "https://w3id.org/okn/o/sd#hasSampleVisualization",
    "baseIri" : "https://w3id.org/okn/o/sd",
    "range" : "134",
    "label" : {
      "IRI-based" : "hasSampleVisualization",
      "en" : "has sample visualization"
    },
    "domain" : "12",
    "comment" : {
      "en" : "A typical sample visualization of the softwware outputs"
    },
    "attributes" : [ "object" ],
    "id" : "133"
  }, {
    "iri" : "https://w3id.org/okn/o/sd#value",
    "baseIri" : "https://w3id.org/okn/o/sd",
    "range" : "137",
    "label" : {
      "IRI-based" : "value",
      "en" : "value"
    },
    "domain" : "136",
    "comment" : {
      "en" : "Value associated to the described entity"
    },
    "attributes" : [ "datatype" ],
    "id" : "135"
  }, {
    "iri" : "https://w3id.org/okn/o/sd#copyrightHolder",
    "baseIri" : "https://w3id.org/okn/o/sd",
    "range" : "17",
    "label" : {
      "IRI-based" : "copyrightHolder",
      "en" : "copyright holder"
    },
    "superproperty" : [ "139" ],
    "domain" : "17",
    "attributes" : [ "object" ],
    "id" : "138"
  }, {
    "iri" : "https://w3id.org/okn/o/sd#memoryRequirements",
    "baseIri" : "https://w3id.org/okn/o/sd",
    "range" : "141",
    "label" : {
      "IRI-based" : "memoryRequirements",
      "en" : "memory requirements"
    },
    "domain" : "12",
    "attributes" : [ "datatype" ],
    "id" : "140"
  }, {
    "iri" : "https://w3id.org/okn/o/sd#hasFormat",
    "baseIri" : "https://w3id.org/okn/o/sd",
    "range" : "144",
    "label" : {
      "IRI-based" : "hasFormat",
      "en" : "has format"
    },
    "domain" : "143",
    "comment" : {
      "en" : "Format followed by a file. For example, txt, nc, etc."
    },
    "attributes" : [ "datatype" ],
    "id" : "142"
  }, {
    "iri" : "https://w3id.org/okn/o/sd#license",
    "baseIri" : "https://w3id.org/okn/o/sd",
    "range" : "147",
    "label" : {
      "IRI-based" : "license",
      "en" : "license"
    },
    "domain" : "146",
    "comment" : {
      "en" : "License of a software component or its source code"
    },
    "attributes" : [ "datatype" ],
    "id" : "145"
  }, {
    "iri" : "http://schema.org/citation",
    "baseIri" : "http://schema.org",
    "range" : "149",
    "annotations" : {
      "isDefinedBy" : [ {
        "identifier" : "isDefinedBy",
        "language" : "undefined",
        "value" : "http://schema.org/",
        "type" : "iri"
      } ]
    },
    "label" : {
      "IRI-based" : "citation"
    },
    "domain" : "17",
    "attributes" : [ "external", "datatype" ],
    "id" : "148"
  }, {
    "iri" : "https://w3id.org/okn/o/sd#hasComponentLocation",
    "baseIri" : "https://w3id.org/okn/o/sd",
    "range" : "151",
    "label" : {
      "IRI-based" : "hasComponentLocation",
      "en" : "has component location"
    },
    "domain" : "7",
    "comment" : {
      "en" : "Location of the aggregation of all the files needed to execute the component. Usually a zip file including the run script and support scripts, including specification files"
    },
    "attributes" : [ "datatype" ],
    "id" : "150"
  }, {
    "iri" : "https://w3id.org/okn/o/sd#hasInstallationInstructions",
    "baseIri" : "https://w3id.org/okn/o/sd",
    "range" : "153",
    "label" : {
      "IRI-based" : "hasInstallationInstructions",
      "en" : "has installation instructions"
    },
    "domain" : "12",
    "comment" : {
      "en" : "Instructions requires to install this particular piece of software."
    },
    "attributes" : [ "datatype" ],
    "id" : "152"
  }, {
    "iri" : "https://w3id.org/okn/o/sd#wasDerivedFromSoftware",
    "baseIri" : "https://w3id.org/okn/o/sd",
    "range" : "12",
    "label" : {
      "IRI-based" : "wasDerivedFromSoftware",
      "en" : "was derived from software"
    },
    "superproperty" : [ "107" ],
    "domain" : "134",
    "attributes" : [ "object" ],
    "id" : "108"
  }, {
    "iri" : "https://w3id.org/okn/o/sd#processorRequirements",
    "baseIri" : "https://w3id.org/okn/o/sd",
    "range" : "155",
    "label" : {
      "IRI-based" : "processorRequirements",
      "en" : "processor requirements"
    },
    "domain" : "12",
    "attributes" : [ "datatype" ],
    "id" : "154"
  }, {
    "iri" : "https://codemeta.github.io/terms/referencePublication",
    "baseIri" : "https://codemeta.github.io/terms",
    "range" : "157",
    "annotations" : {
      "isDefinedBy" : [ {
        "identifier" : "isDefinedBy",
        "language" : "undefined",
        "value" : "https://codemeta.github.io/terms/",
        "type" : "iri"
      } ]
    },
    "label" : {
      "IRI-based" : "referencePublication"
    },
    "domain" : "17",
    "attributes" : [ "external", "datatype" ],
    "id" : "156"
  }, {
    "iri" : "https://w3id.org/okn/o/sd#hasMaximumAcceptedValue",
    "baseIri" : "https://w3id.org/okn/o/sd",
    "range" : "160",
    "label" : {
      "IRI-based" : "hasMaximumAcceptedValue",
      "en" : "has maximum accepted value"
    },
    "domain" : "159",
    "comment" : {
      "en" : "Maximum accepted value of a variable presentation (or a parameter)"
    },
    "attributes" : [ "datatype" ],
    "id" : "158"
  }, {
    "iri" : "https://w3id.org/okn/o/sd#hasPart",
    "baseIri" : "https://w3id.org/okn/o/sd",
    "range" : "8",
    "label" : {
      "IRI-based" : "hasPart",
      "en" : "has part"
    },
    "domain" : "26",
    "comment" : {
      "en" : "Property designed to reference the elements included in a sample collection."
    },
    "attributes" : [ "object" ],
    "id" : "161"
  }, {
    "iri" : "https://w3id.org/okn/o/sd#datePublished",
    "baseIri" : "https://w3id.org/okn/o/sd",
    "range" : "163",
    "label" : {
      "IRI-based" : "datePublished",
      "en" : "date published"
    },
    "domain" : "12",
    "attributes" : [ "datatype" ],
    "id" : "162"
  }, {
    "iri" : "https://w3id.org/okn/o/sd#hasSourceCode",
    "baseIri" : "https://w3id.org/okn/o/sd",
    "range" : "50",
    "label" : {
      "IRI-based" : "hasSourceCode",
      "en" : "has source code"
    },
    "domain" : "12",
    "attributes" : [ "functional", "object" ],
    "id" : "166"
  }, {
    "iri" : "https://w3id.org/okn/o/sd#adjustsVariable",
    "baseIri" : "https://w3id.org/okn/o/sd",
    "range" : "120",
    "label" : {
      "IRI-based" : "adjustsVariable",
      "en" : "adjusts variable"
    },
    "domain" : "69",
    "comment" : {
      "en" : "Property that links parameter with the variable they adjust. This property can be used when parameters quantify variables without directly representing them. For example, a \"fertilizer percentage adjustment\" parameter can quantify a \"fertilizer price\" variable"
    },
    "attributes" : [ "functional", "object" ],
    "id" : "168"
  }, {
    "iri" : "https://w3id.org/okn/o/sd#hasInput",
    "baseIri" : "https://w3id.org/okn/o/sd",
    "range" : "1",
    "label" : {
      "IRI-based" : "hasInput",
      "en" : "has input"
    },
    "domain" : "7",
    "comment" : {
      "en" : "Property that links a model configuration to the input types expected by it."
    },
    "attributes" : [ "object" ],
    "id" : "169"
  }, {
    "iri" : "https://w3id.org/okn/o/sd#screenshot",
    "baseIri" : "https://w3id.org/okn/o/sd",
    "range" : "53",
    "label" : {
      "IRI-based" : "screenshot"
    },
    "superproperty" : [ "98" ],
    "domain" : "12",
    "attributes" : [ "object" ],
    "id" : "99"
  }, {
    "iri" : "https://w3id.org/okn/o/sd#hasDocumentation",
    "baseIri" : "https://w3id.org/okn/o/sd",
    "range" : "167",
    "label" : {
      "IRI-based" : "hasDocumentation",
      "en" : "has documentation"
    },
    "domain" : "12",
    "comment" : {
      "en" : "Pointer to the documentation of the model"
    },
    "attributes" : [ "datatype" ],
    "id" : "173"
  }, {
    "iri" : "https://w3id.org/okn/o/sd#hasLongName",
    "baseIri" : "https://w3id.org/okn/o/sd",
    "range" : "175",
    "label" : {
      "IRI-based" : "hasLongName",
      "en" : "has long name"
    },
    "domain" : "10",
    "comment" : {
      "en" : "Properties that relate the variable representation to its long name. The long name is useful for context (e.g., precipitation is less ambiguous than P) but not as precise as the standard name."
    },
    "attributes" : [ "datatype" ],
    "id" : "174"
  }, {
    "iri" : "http://schema.org/publisher",
    "baseIri" : "http://schema.org",
    "range" : "17",
    "annotations" : {
      "isDefinedBy" : [ {
        "identifier" : "isDefinedBy",
        "language" : "undefined",
        "value" : "http://schema.org/",
        "type" : "iri"
      } ]
    },
    "label" : {
      "IRI-based" : "publisher"
    },
    "domain" : "17",
    "subproperty" : [ "114" ],
    "attributes" : [ "external", "object" ],
    "id" : "116"
  }, {
    "iri" : "https://w3id.org/okn/o/sd#hasDefaultValue",
    "baseIri" : "https://w3id.org/okn/o/sd",
    "range" : "181",
    "label" : {
      "IRI-based" : "hasDefaultValue",
      "en" : "has default value"
    },
    "domain" : "172",
    "comment" : {
      "en" : "Default accepted value of a variable presentation (or a parameter)"
    },
    "attributes" : [ "datatype" ],
    "id" : "180"
  }, {
    "iri" : "https://w3id.org/okn/o/sd#hasStandardVariable",
    "baseIri" : "https://w3id.org/okn/o/sd",
    "range" : "38",
    "label" : {
      "IRI-based" : "hasStandardVariable",
      "en" : "has standard variable"
    },
    "domain" : "183",
    "comment" : {
      "en" : "the standard name of a variable"
    },
    "attributes" : [ "functional", "object" ],
    "id" : "182"
  }, {
    "iri" : "https://w3id.org/okn/o/sd#fundingGrant",
    "baseIri" : "https://w3id.org/okn/o/sd",
    "range" : "178",
    "label" : {
      "IRI-based" : "fundingGrant",
      "en" : "funding grant"
    },
    "domain" : "117",
    "comment" : {
      "en" : "Grant number used for funding"
    },
    "attributes" : [ "datatype" ],
    "id" : "184"
  }, {
    "iri" : "http://www.w3.org/ns/prov#hadPrimarySource",
    "baseIri" : "http://www.w3.org/ns/prov",
    "range" : "17",
    "annotations" : {
      "isDefinedBy" : [ {
        "identifier" : "isDefinedBy",
        "language" : "undefined",
        "value" : "http://www.w3.org/ns/prov#",
        "type" : "iri"
      } ]
    },
    "label" : {
      "IRI-based" : "hadPrimarySource"
    },
    "domain" : "17",
    "subproperty" : [ "125" ],
    "attributes" : [ "external", "object" ],
    "id" : "128"
  }, {
    "iri" : "http://schema.org/memoryRequirements",
    "baseIri" : "http://schema.org",
    "range" : "188",
    "annotations" : {
      "isDefinedBy" : [ {
        "identifier" : "isDefinedBy",
        "language" : "undefined",
        "value" : "http://schema.org/",
        "type" : "iri"
      } ]
    },
    "label" : {
      "IRI-based" : "memoryRequirements"
    },
    "domain" : "12",
    "attributes" : [ "external", "datatype" ],
    "id" : "187"
  }, {
    "iri" : "http://schema.org/author",
    "baseIri" : "http://schema.org",
    "range" : "17",
    "annotations" : {
      "isDefinedBy" : [ {
        "identifier" : "isDefinedBy",
        "language" : "undefined",
        "value" : "http://schema.org/",
        "type" : "iri"
      } ]
    },
    "label" : {
      "IRI-based" : "author"
    },
    "domain" : "17",
    "subproperty" : [ "84" ],
    "attributes" : [ "external", "object" ],
    "id" : "86"
  }, {
    "iri" : "https://w3id.org/okn/o/sd#hasSetup",
    "baseIri" : "https://w3id.org/okn/o/sd",
    "range" : "41",
    "label" : {
      "IRI-based" : "hasSetup",
      "en" : "has setup"
    },
    "domain" : "7",
    "comment" : {
      "en" : "Property used to define configurations with some fixed resources and values. The rationale of this property is to allow predefined configurations"
    },
    "attributes" : [ "object" ],
    "id" : "189"
  }, {
    "iri" : "https://w3id.org/okn/o/sd#hasParameter",
    "baseIri" : "https://w3id.org/okn/o/sd",
    "range" : "69",
    "label" : {
      "IRI-based" : "hasParameter",
      "en" : "has parameter"
    },
    "domain" : "7",
    "comment" : {
      "en" : "Property that indicates the parameters of a model configuration"
    },
    "attributes" : [ "object" ],
    "id" : "190"
  }, {
    "iri" : "http://schema.org/email",
    "baseIri" : "http://schema.org",
    "range" : "192",
    "annotations" : {
      "isDefinedBy" : [ {
        "identifier" : "isDefinedBy",
        "language" : "undefined",
        "value" : "http://schema.org/",
        "type" : "iri"
      } ]
    },
    "label" : {
      "IRI-based" : "email"
    },
    "domain" : "17",
    "attributes" : [ "external", "datatype" ],
    "id" : "191"
  }, {
    "iri" : "https://w3id.org/okn/o/sd#name",
    "baseIri" : "https://w3id.org/okn/o/sd",
    "range" : "186",
    "label" : {
      "IRI-based" : "name",
      "en" : "name"
    },
    "domain" : "17",
    "comment" : {
      "en" : "Name of the resource"
    },
    "attributes" : [ "datatype" ],
    "id" : "193"
  }, {
    "iri" : "https://w3id.org/okn/o/sd#hasFunding",
    "baseIri" : "https://w3id.org/okn/o/sd",
    "range" : "117",
    "label" : {
      "IRI-based" : "hasFunding",
      "en" : "has funding information"
    },
    "domain" : "12",
    "comment" : {
      "en" : "Property that links a software project to its funding information"
    },
    "attributes" : [ "object" ],
    "id" : "197"
  }, {
    "iri" : "https://w3id.org/okn/o/sd#hasFixedValue",
    "baseIri" : "https://w3id.org/okn/o/sd",
    "range" : "199",
    "label" : {
      "IRI-based" : "hasFixedValue",
      "en" : "has fixed value"
    },
    "domain" : "69",
    "comment" : {
      "en" : "Value of a parameter in a software setup."
    },
    "attributes" : [ "datatype" ],
    "id" : "198"
  }, {
    "iri" : "http://schema.org/operatingSystems",
    "baseIri" : "http://schema.org",
    "range" : "201",
    "annotations" : {
      "isDefinedBy" : [ {
        "identifier" : "isDefinedBy",
        "language" : "undefined",
        "value" : "http://schema.org/",
        "type" : "iri"
      } ]
    },
    "label" : {
      "IRI-based" : "operatingSystems"
    },
    "domain" : "17",
    "attributes" : [ "external", "datatype" ],
    "id" : "200"
  }, {
    "iri" : "https://w3id.org/okn/o/sd#contributor",
    "baseIri" : "https://w3id.org/okn/o/sd",
    "range" : "29",
    "label" : {
      "IRI-based" : "contributor",
      "en" : "contributor"
    },
    "superproperty" : [ "203" ],
    "domain" : "12",
    "attributes" : [ "object" ],
    "id" : "202"
  }, {
    "iri" : "https://w3id.org/okn/o/sd#hasConstraint",
    "baseIri" : "https://w3id.org/okn/o/sd",
    "range" : "170",
    "label" : {
      "IRI-based" : "hasConstraint",
      "en" : "has constraint"
    },
    "domain" : "171",
    "comment" : {
      "en" : "Constraint or rule associated to a  variable or software configuration. For example: \"This model accepts only monthly data\", or \"all inputs of this model configuration must share the same location\". More structured restrictions, such as Jena rules or SWRL rules may also be captured with this property"
    },
    "attributes" : [ "datatype" ],
    "id" : "204"
  }, {
    "iri" : "https://w3id.org/okn/o/sd#keywords",
    "baseIri" : "https://w3id.org/okn/o/sd",
    "range" : "194",
    "label" : {
      "IRI-based" : "keywords",
      "en" : "keywords"
    },
    "domain" : "12",
    "comment" : {
      "en" : "Keywords associated with a software component"
    },
    "attributes" : [ "datatype" ],
    "id" : "206"
  }, {
    "iri" : "https://w3id.org/okn/o/sd#hasConfiguration",
    "baseIri" : "https://w3id.org/okn/o/sd",
    "range" : "7",
    "label" : {
      "IRI-based" : "hasConfiguration",
      "en" : "has configuration"
    },
    "domain" : "32",
    "comment" : {
      "en" : "Property that links a model to one of its configurations. A model may have multiple configurations, each of which is unique in terms of the inputs and outputs it uses."
    },
    "attributes" : [ "object" ],
    "id" : "208"
  }, {
    "iri" : "https://w3id.org/okn/o/sd#website",
    "baseIri" : "https://w3id.org/okn/o/sd",
    "range" : "211",
    "label" : {
      "IRI-based" : "website",
      "en" : "website"
    },
    "domain" : "210",
    "comment" : {
      "en" : "Website of the software"
    },
    "attributes" : [ "datatype" ],
    "id" : "209"
  }, {
    "iri" : "http://www.w3.org/ns/prov#used",
    "baseIri" : "http://www.w3.org/ns/prov",
    "range" : "17",
    "annotations" : {
      "isDefinedBy" : [ {
        "identifier" : "isDefinedBy",
        "language" : "undefined",
        "value" : "http://www.w3.org/ns/prov#",
        "type" : "iri"
      } ]
    },
    "label" : {
      "IRI-based" : "used"
    },
    "domain" : "17",
    "attributes" : [ "external", "object" ],
    "id" : "212"
  }, {
    "iri" : "https://w3id.org/okn/o/sd#hasUsageNotes",
    "baseIri" : "https://w3id.org/okn/o/sd",
    "range" : "195",
    "label" : {
      "IRI-based" : "hasUsageNotes",
      "en" : "has usage notes"
    },
    "domain" : "12",
    "comment" : {
      "en" : "Property that describes the usage considerations of a particular software. These notes capture the rationale of for that software configuration, along with an explanation for sample inputs, things to consider when running the model with data, etc."
    },
    "attributes" : [ "datatype" ],
    "id" : "213"
  }, {
    "iri" : "http://schema.org/identifier",
    "baseIri" : "http://schema.org",
    "range" : "215",
    "annotations" : {
      "isDefinedBy" : [ {
        "identifier" : "isDefinedBy",
        "language" : "undefined",
        "value" : "http://schema.org/",
        "type" : "iri"
      } ]
    },
    "label" : {
      "IRI-based" : "identifier"
    },
    "domain" : "17",
    "attributes" : [ "external", "datatype" ],
    "id" : "214"
  }, {
    "iri" : "http://schema.org/datePublished",
    "baseIri" : "http://schema.org",
    "range" : "217",
    "annotations" : {
      "isDefinedBy" : [ {
        "identifier" : "isDefinedBy",
        "language" : "undefined",
        "value" : "http://schema.org/",
        "type" : "iri"
      } ]
    },
    "label" : {
      "IRI-based" : "datePublished"
    },
    "domain" : "17",
    "attributes" : [ "external", "datatype" ],
    "id" : "216"
  }, {
    "iri" : "http://schema.org/processorRequirements",
    "baseIri" : "http://schema.org",
    "range" : "219",
    "annotations" : {
      "isDefinedBy" : [ {
        "identifier" : "isDefinedBy",
        "language" : "undefined",
        "value" : "http://schema.org/",
        "type" : "iri"
      } ]
    },
    "label" : {
      "IRI-based" : "processorRequirements"
    },
    "domain" : "17",
    "attributes" : [ "external", "datatype" ],
    "id" : "218"
  }, {
    "iri" : "https://w3id.org/okn/o/sd#position",
    "baseIri" : "https://w3id.org/okn/o/sd",
    "range" : "222",
    "label" : {
      "IRI-based" : "position",
      "en" : "position"
    },
    "domain" : "221",
    "comment" : {
      "en" : "Position of the parameter or input/output in the model configuration. This property is needed to know how to organize the I/O of the component on execution"
    },
    "attributes" : [ "datatype" ],
    "id" : "220"
  }, {
    "iri" : "https://w3id.org/okn/o/sd#usefulForCalculatingIndex",
    "baseIri" : "https://w3id.org/okn/o/sd",
    "range" : "39",
    "label" : {
      "IRI-based" : "usefulForCalculatingIndex",
      "undefined" : "useful for calculating index"
    },
    "domain" : "12",
    "comment" : {
      "en" : "Property that indicates that a software component (or any of its outputs) can be used to calculate a particular index. The rationale for this property is that indices are usually calculated by applying post-processing steps to the outputs of a software component."
    },
    "attributes" : [ "object" ],
    "id" : "225"
  }, {
    "iri" : "https://w3id.org/okn/o/sd#hasDataTransformation",
    "baseIri" : "https://w3id.org/okn/o/sd",
    "range" : "36",
    "label" : {
      "IRI-based" : "hasDataTransformation",
      "en" : "has data transformation"
    },
    "domain" : "1",
    "subproperty" : [ "227" ],
    "comment" : {
      "en" : "Property that associates an input/output with their corresponding data transformation."
    },
    "attributes" : [ "object" ],
    "id" : "226"
  }, {
    "iri" : "https://w3id.org/okn/o/sd#description",
    "baseIri" : "https://w3id.org/okn/o/sd",
    "range" : "176",
    "label" : {
      "IRI-based" : "description",
      "en" : "description"
    },
    "domain" : "177",
    "comment" : {
      "en" : "A description of a resource"
    },
    "attributes" : [ "datatype" ],
    "id" : "228"
  }, {
    "iri" : "https://w3id.org/okn/o/sd#hasContactPerson",
    "baseIri" : "https://w3id.org/okn/o/sd",
    "range" : "230",
    "label" : {
      "IRI-based" : "hasContactPerson",
      "en" : "has contact person"
    },
    "domain" : "12",
    "attributes" : [ "object" ],
    "id" : "229"
  }, {
    "iri" : "https://w3id.org/okn/o/sd#tag",
    "baseIri" : "https://w3id.org/okn/o/sd",
    "range" : "223",
    "label" : {
      "IRI-based" : "tag",
      "en" : "tag"
    },
    "domain" : "224",
    "comment" : {
      "en" : "Tag used to annotate a version or a software configuration. This annotation is useful to show which version is the latest, or which version is deprecated. Supported tags are: \"latest\", \"deprecated\""
    },
    "attributes" : [ "datatype" ],
    "id" : "231"
  }, {
    "range" : "37",
    "domain" : "38",
    "attributes" : [ "anonymous", "object" ],
    "id" : "232"
  }, {
    "iri" : "http://www.w3.org/ns/prov#wasGeneratedBy",
    "baseIri" : "http://www.w3.org/ns/prov",
    "range" : "17",
    "annotations" : {
      "isDefinedBy" : [ {
        "identifier" : "isDefinedBy",
        "language" : "undefined",
        "value" : "http://www.w3.org/ns/prov#",
        "type" : "iri"
      } ]
    },
    "label" : {
      "IRI-based" : "wasGeneratedBy"
    },
    "domain" : "17",
    "attributes" : [ "external", "object" ],
    "id" : "233"
  }, {
    "range" : "8",
    "domain" : "26",
    "attributes" : [ "anonymous", "object" ],
    "id" : "234"
  }, {
    "range" : "37",
    "domain" : "10",
    "attributes" : [ "anonymous", "object" ],
    "id" : "235"
  }, {
    "range" : "37",
    "domain" : "39",
    "attributes" : [ "anonymous", "object" ],
    "id" : "236"
  }, {
    "range" : "19",
    "domain" : "20",
    "attributes" : [ "anonymous", "object" ],
    "id" : "238"
  }, {
    "iri" : "https://w3id.org/okn/o/sd#hasExecutionCommand",
    "baseIri" : "https://w3id.org/okn/o/sd",
    "range" : "164",
    "label" : {
      "IRI-based" : "hasExecutionCommand",
      "en" : "has execution command"
    },
    "domain" : "165",
    "comment" : {
      "en" : "Execution instructions on how to run the image"
    },
    "attributes" : [ "datatype" ],
    "id" : "241"
  }, {
    "iri" : "https://w3id.org/okn/o/sd#hasSampleExecution",
    "baseIri" : "https://w3id.org/okn/o/sd",
    "range" : "44",
    "label" : {
      "IRI-based" : "hasSampleExecution",
      "en" : "has sample execution"
    },
    "domain" : "7",
    "attributes" : [ "object" ],
    "id" : "242"
  }, {
    "iri" : "https://w3id.org/okn/o/sd#operatingSystems",
    "baseIri" : "https://w3id.org/okn/o/sd",
    "range" : "185",
    "label" : {
      "IRI-based" : "operatingSystems",
      "en" : "operating systems"
    },
    "domain" : "12",
    "attributes" : [ "datatype" ],
    "id" : "244"
  }, {
    "iri" : "https://w3id.org/okn/o/sd#hasPresentation",
    "inverse" : "9",
    "baseIri" : "https://w3id.org/okn/o/sd",
    "range" : "10",
    "label" : {
      "IRI-based" : "hasPresentation",
      "en" : "has presentation"
    },
    "domain" : "240",
    "comment" : {
      "en" : "Property that links an instance of a dataset (or a dataset specification) to the presentation of a variable contained (or expected to be contained) on it."
    },
    "attributes" : [ "object" ],
    "id" : "245"
  }, {
    "iri" : "http://schema.org/contributor",
    "baseIri" : "http://schema.org",
    "range" : "17",
    "annotations" : {
      "isDefinedBy" : [ {
        "identifier" : "isDefinedBy",
        "language" : "undefined",
        "value" : "http://schema.org/",
        "type" : "iri"
      } ]
    },
    "label" : {
      "IRI-based" : "contributor"
    },
    "domain" : "17",
    "subproperty" : [ "202" ],
    "attributes" : [ "external", "object" ],
    "id" : "203"
  }, {
    "iri" : "http://schema.org/license",
    "baseIri" : "http://schema.org",
    "range" : "247",
    "annotations" : {
      "isDefinedBy" : [ {
        "identifier" : "isDefinedBy",
        "language" : "undefined",
        "value" : "http://schema.org/",
        "type" : "iri"
      } ]
    },
    "label" : {
      "IRI-based" : "license"
    },
    "domain" : "17",
    "attributes" : [ "external", "datatype" ],
    "id" : "246"
  }, {
    "iri" : "http://schema.org/dateCreated",
    "baseIri" : "http://schema.org",
    "range" : "249",
    "annotations" : {
      "isDefinedBy" : [ {
        "identifier" : "isDefinedBy",
        "language" : "undefined",
        "value" : "http://schema.org/",
        "type" : "iri"
      } ]
    },
    "label" : {
      "IRI-based" : "dateCreated"
    },
    "domain" : "17",
    "attributes" : [ "external", "datatype" ],
    "id" : "248"
  }, {
    "iri" : "http://schema.org/softwareRequirements",
    "baseIri" : "http://schema.org",
    "range" : "251",
    "annotations" : {
      "isDefinedBy" : [ {
        "identifier" : "isDefinedBy",
        "language" : "undefined",
        "value" : "http://schema.org/",
        "type" : "iri"
      } ]
    },
    "label" : {
      "IRI-based" : "softwareRequirements"
    },
    "domain" : "17",
    "attributes" : [ "external", "datatype" ],
    "id" : "250"
  }, {
    "iri" : "https://w3id.org/okn/o/sd#hasFixedResource",
    "baseIri" : "https://w3id.org/okn/o/sd",
    "range" : "8",
    "label" : {
      "IRI-based" : "hasFixedResource",
      "en" : "has fixed resource"
    },
    "domain" : "1",
    "comment" : {
      "en" : "Property that links a parameter or an input to a fixed value. For example, in a given configuration a parameter with the planting date for a model could be fixed to avoid the user changing it for that region."
    },
    "attributes" : [ "object" ],
    "id" : "252"
  }, {
    "iri" : "https://w3id.org/okn/o/sd#hasTypicalDataSource",
    "baseIri" : "https://w3id.org/okn/o/sd",
    "range" : "196",
    "label" : {
      "IRI-based" : "hasTypicalDataSource",
      "en" : "has typical data source"
    },
    "domain" : "12",
    "attributes" : [ "datatype" ],
    "id" : "253"
  }, {
    "iri" : "https://w3id.org/okn/o/sd#hasImplementationScriptLocation",
    "baseIri" : "https://w3id.org/okn/o/sd",
    "range" : "207",
    "label" : {
      "IRI-based" : "hasImplementationScriptLocation",
      "en" : "has implementation script location"
    },
    "domain" : "7",
    "comment" : {
      "en" : "Property that points to the main runnable script for the current function"
    },
    "attributes" : [ "datatype" ],
    "id" : "254"
  }, {
    "iri" : "http://schema.org/copyrightHolder",
    "baseIri" : "http://schema.org",
    "range" : "17",
    "annotations" : {
      "isDefinedBy" : [ {
        "identifier" : "isDefinedBy",
        "language" : "undefined",
        "value" : "http://schema.org/",
        "type" : "iri"
      } ]
    },
    "label" : {
      "IRI-based" : "copyrightHolder"
    },
    "domain" : "17",
    "subproperty" : [ "138" ],
    "attributes" : [ "external", "object" ],
    "id" : "139"
  }, {
    "iri" : "https://w3id.org/okn/o/sd#hasDataTransformationSetup",
    "baseIri" : "https://w3id.org/okn/o/sd",
    "range" : "47",
    "label" : {
      "IRI-based" : "hasDataTransformationSetup",
      "en" : "has data transformation setup"
    },
    "superproperty" : [ "226" ],
    "domain" : "1",
    "comment" : {
      "en" : "Property to link an input/output dataset to the specific data transformation (with URLs"
    },
    "attributes" : [ "object" ],
    "id" : "227"
  }, {
    "iri" : "https://w3id.org/okn/o/sd#codeRepository",
    "baseIri" : "https://w3id.org/okn/o/sd",
    "range" : "243",
    "label" : {
      "IRI-based" : "codeRepository",
      "en" : "code repository"
    },
    "domain" : "50",
    "comment" : {
      "en" : "URL to the code repository of a software component"
    },
    "attributes" : [ "datatype" ],
    "id" : "255"
  }, {
    "iri" : "https://w3id.org/okn/o/sd#email",
    "baseIri" : "https://w3id.org/okn/o/sd",
    "range" : "179",
    "label" : {
      "IRI-based" : "email",
      "en" : "email"
    },
    "domain" : "29",
    "attributes" : [ "datatype" ],
    "id" : "256"
  }, {
    "iri" : "https://w3id.org/okn/o/sd#hasMinimumAcceptedValue",
    "baseIri" : "https://w3id.org/okn/o/sd",
    "range" : "237",
    "label" : {
      "IRI-based" : "hasMinimumAcceptedValue",
      "en" : "has minimum accepted value"
    },
    "domain" : "205",
    "comment" : {
      "en" : "Minimum accepted value of a variable presentation (or a parameter)"
    },
    "attributes" : [ "datatype" ],
    "id" : "257"
  }, {
    "iri" : "https://codemeta.github.io/terms/funding",
    "baseIri" : "https://codemeta.github.io/terms",
    "range" : "239",
    "annotations" : {
      "isDefinedBy" : [ {
        "identifier" : "isDefinedBy",
        "language" : "undefined",
        "value" : "https://codemeta.github.io/terms/",
        "type" : "iri"
      } ]
    },
    "label" : {
      "IRI-based" : "funding"
    },
    "domain" : "17",
    "attributes" : [ "external", "datatype" ],
    "id" : "258"
  }, {
    "iri" : "https://w3id.org/okn/o/sd#compatibleVisualizationSoftware",
    "baseIri" : "https://w3id.org/okn/o/sd",
    "range" : "12",
    "label" : {
      "IRI-based" : "compatibleVisualizationSoftware",
      "undefined" : "compatible visualization software"
    },
    "domain" : "12",
    "comment" : {
      "en" : "Property that links a software component to other useful software that canbe used to visualize its outputs"
    },
    "attributes" : [ "object" ],
    "id" : "259"
  } ]
}